{
  "nikaya": "ඉතිවුත්තක පාළි",
  "vagga": "1.2.10. පදුට්ඨපුග්ගල සුත්තං",
  "sutta_title": "1.2.10. දූෂිත සිත් ඇති පුද්ගලයා ගැන වදාළ දෙසුම",
  "description": "",
  "pali": "වුත්තං හේතං භගවතා, වුත්තමරහතා’ති මේ සුතං. ඉධාහං භික්ඛවේ ඒකච්චං පුග්ගලං පදුට්ඨචිත්තං ඒවං චේතසා චේතෝ පරිච්ච පජානාමි: ‘ඉමම්හි චායං සමයේ පුග්ගලෝ කාලංකරෙය්‍ය, යථාභතං නික්ඛිත්තෝ, ඒවං නිරයේ’. තං කිස්ස හේතු? චිත්තඤ්හි’ස්ස භික්ඛවේ පදුට්ඨං. චේතෝපදෝසහේතු ඛෝ පන භික්ඛවේ ඒවමිධේකච්චේ සත්තා කායස්ස භේදා පරං මරණා අපායං දුග්ගතිං විනිපාතං නිරයං උපපජ්ජන්තී’ති. ඒතමත්ථං භගවා අවෝච. තත්ථේතං ඉති වුච්චති: අයම්පි අත්ථෝ වුත්තෝ භගවතා ඉති මේ සුතන්ති. තස්සුද්දානං: මෝහෝ කෝධෝ අථ මක්ඛෝ විජ්ජා තණ්හා සේඛා දුවේ,භේදෝ සාමග්ගිපුග්ගලෝ ච වග්ගමාහු දුතියන්ති වුච්චති.",
  "sinhala": "භාග්‍යවතුන් වහන්සේ තමයි මේ කාරණය වදාළේ. අරහත් මුනිඳාණන්මයි මෙය වදාළේ. මේ විදිහටයි මට අසන්නට ලැබුනේ. “පින්වත් මහණෙනි, මේ ලෝකයේ ඉන්න දූෂිත වෙච්ච සිත් ඇති සමහර පුද්ගලයන්ගේ සිත මගේ සිතින් මේ විදිහට දැනගන්නවා. මේ පුද්ගලයා මේ කාලෙ මිය පරලොව ගියොත්, හරියට හිසින් ගත් බරක් බිමින් තියනවා වගේ නිරයේ තමයි උපදින්නේ. ඒකට හේතුව මොකක්ද? පින්වත් මහණෙනි, ඒ ඔහුගේ සිත දූෂිත වෙච්ච නිසා. පින්වත් මහණෙනි, සිත දූෂිත වීම නිසාම මේ ලෝකයේ සමහර උදවිය කය බිඳිලා මැරුණට පස්සේ සැප නැති, දුගතිය වූ, විනිපාත නිරයේ උපදිනවා.” මේ අර්ථය භාග්‍යවතුන් වහන්සේ වදාළ සේක. එය මේ අයුරිනුත් පවසන්න පුළුවනි. “මෙහි ඇතැම් පුද්ගලයන්ගේ දූෂිත සිත ගැන දැන වදාළ බුදුරජාණන් වහන්සේ ඒ ගැන භික්ෂූන් සමීපයෙහි පවසා වදාළා. මේ පුද්ගලයා මේ වෙලාවේ කළුරිය කළොත්, ඔහු නිරයේ තමයි උපදින්නේ. ඒ ඔහුගේ සිත දූෂිත වෙච්ච නිසා. හරියට ගෙන ආපු යම් දෙයක් බිමින් තබනවාද, අන්න ඒ වගේමයි. මේ සිත දූෂිත වීම කියන හේතුව නිසාම තමයි සත්වයන් දුගතියට යන්නේ.” මේ අර්ථය වදාරණ ලද්දේ භාග්‍යවතුන් වහන්සේ විසින්මයි. මේ විදිහට මා හට අසන්නට ලැබුනා.",
  "ai_short_intro": "සිතෙහි දූෂණය හේතුවෙන් මරණයෙන් පසු දුගී උපත ලැබීමේ ස්වභාවය",
  "ai_detailed_summary": "අරහත් මුනිඳුන් වහන්සේ විසින් දේශනා කරන ලද ප්‍රධානම දේශනාව වූයේ, ලෝකයේ පවතින දූෂිත චේතනාවන් ඇති පුද්ගලයන්ගේ අනාගත උපත පිළිබඳවය. මෙම දේශනාව තුළින් ප්‍රකාශ කෙරෙන්නේ, යමෙකුගේ සිත දූෂිත වීම ප්‍රධාන හේතුව බවයි.\n\nමෙම දූෂිත සිතුවිලි හේතුවෙන්, ජීවිතයේදී මරණයට පත්වීමෙන් පසු, එම පුද්ගලයා සුවපහසු ජීවිතයකට නොව, දුගතියෙන් පිරි, සැප නැති, විනිපාත නිරයේ උපදින බව අරහත් මුනිඳුන් වහන්සේ විසින් පැහැදිලිව වදාළ ලදී.\n\nඑම අදහස වෙනත් ආකාරයකින් ද ප්‍රකාශ කළ විට, බුදුරජාණන් වහන්සේ විසින් භික්ෂූන් වහන්සේලා සමීපයේදී දේශනා කළ ආකාරයටම, ඇතැම් පුද්ගලයන්ගේ දූෂිත සිත ගැන දැන වදාළ බව සඳහන් වේ. මෙහිදී අවධාරණය කරනු ලබන්නේ, වර්තමානයේ යම් ක්‍රියාවක් කිරීම හෝ චේතනාවක් පැවතීම නිසා, මරණයෙන් පසු නිරයේ උපත සිදුවන බවයි.\n\nසාරාංශයක් ලෙස, සත්වයන් දුගතියට යෑමට මූලික හේතුව වන්නේ ඔවුන්ගේ සිත දූෂිත වීමයි. මෙම දූෂිත චේතනාවන් නිසා, මරණයෙන් පසු ලැබෙන ප්‍රතිඵලය නිරයේ උපත වීම බව අරහත් මුනිඳුන් වහන්සේ විසින් නැවත නැවතත් අවධාරණය කරමින් දේශනා කර ඇත."
}