{
  "nikaya": "ථේරී ගාථා",
  "vagga": "6.5. අනුපමා ථේරීගාථා",
  "sutta_title": "6.5. අනුපමා තෙරණියගේ ගාථා",
  "description": "",
  "pali": "ඉත්ථං සුදං අනෝපමා ථේරී ගාථායෝ අභාසීති.",
  "sinhala": "151. මං ඉපදුනේ ගොඩාක් සැප සම්පත් තියෙන ධනවත්, උසස් පවුලක. මං මේඝ සිටුතුමාගේ දුව. මං ඒ කාලෙ හරි ම ලස්සනයි. 152. රාජ කුමාරයන්, සිටු කුමාරයන් මට ගොඩාක් කැමති වුණා. “අනුපමා දුව මට පාවා දෙන්න” කියල අපේ පියාට දූතයන් පවා එව්වා. 153. ඔබේ අනුපමා දුව තරාදියේ එක පැත්තක තියල, අනිත් පැත්තේ ඒ බරට ධනය ලබාගෙන නම් දෙන්නෙ, අපි ඊට වඩා අට ගුණයක් රන් මැණික් දෙනවා. 154. නමුත් මුළු ලෝකෙට ම ජ්‍යෙෂ්ඨ වූ අනුත්තර වූ බුදු සමිඳුන්ව මං දැකගත්තා. උන්වහන්සේ ගේ සිරිපා කමල් වන්දනා කළා. එකත්පස්ව හිඳ ගත්තා. 155. ගෞතම බුදු සමිඳුන් මං ගැන අනුකම්පාවෙන් මට ධර්මය දේශනා කළා. මං ඒ ආසනයේදීම අනාගාමී ඵලයට පත් වුණා. 156. ඊට පස්සෙ මං කෙස් මුඩු කර ගෙන, සසුන්ගත වුණා. තෘෂ්ණාව නැති කරල දාලා අදට දින හතක් වෙනවා. මේ වනාහී අනුපමා නම් රහත් තෙරණිය වදාළ ගාථාවන් ය.",
  "ai_short_intro": "සාරවත් ජීවිතයක් අත්හැර බුද්ධ ධර්මයට යොමු වීමෙන් උතුම් ඵලයන් අත්පත් කරගැනීම",
  "ai_detailed_summary": "මම උපත ලැබුවේ බොහෝ සැප සම්පත් සහිත ධනවත්, උසස් පවුලක ය. මම මේඝ සිටුතුමාගේ දුව ලෙස හැදී වැඩුණි. මගේ ජීවිතයේ ආරම්භයේදී මට රාජ කුමාරයන් සහ සිටු කුමාරයන් පිළිබඳ දැඩි කැමැත්තක් ඇති විය. මෙම කැමැත්ත නිසා අපගේ පියා දූතයන් යවා අනුපමා දුවක් ලබාගැනීමට ඉල්ලා සිටියේය. මෙම දුව ලබාගැනීම සම්බන්ධයෙන්, ධනය පිළිබඳ ගනුදෙනුවක් ඉදිරිපත් විය. එනම්, අනුපමා දුව තරාදියේ එක පැත්තක තබා, අනෙක් පැත්තේ ඒ බරට ධනය ලබාගැනීම සඳහා අට ගුණයක් රන් මැණික් දීමට යෝජනා විය.\n\nඑම අතරතුර, මම ලෝකයේ ජ්‍යෙෂ්ඨතම, අනුත්තර වූ බුදු සමිඳුන්ව දැකගත්තා. මම උන්වහන්සේගේ සිරිපා කමල් වන්දනා කර, එකත්පස්ව හිඳ ගත්තා. ගෞතම බුදු සමිඳුන් මගේ තත්ත්වය ගැන අනුකම්පාවෙන් මට ධර්මය දේශනා කළ අතර, මම එම ආසනයේදීම අනාගාමී ඵලයට පත් වුණා.\n\nඉන්පසුව මම කෙස් මුඩු කරගෙන සසුන්ගත වීමට තීරණය කළ අතර, තෘෂ්ණාව නැති කරගැනීම සඳහා දාලා අදට දින හතක් වෙනවා. මෙම අනුපමා නම් රහත් තෙරණිය විසින් වදාළ ගාථාවන් මගින් විස්තර කෙරේ."
}