{
  "nikaya": "සංයුත්ත නිකාය",
  "vagga": "මහා වග්ගෝ",
  "sutta_title": "12.8.8. බීජගාම සූත්‍රය",
  "description": "ගස් කොළන් සිඳලීම ගැන වදාළ දෙසුම",
  "pali": "ඒවමේව ඛෝ භික්ඛවේ, අප්පකා තේ සත්තා යේ බීජගාමභූතගාමසමාරම්භා පටිවිරතා. අථ ඛෝ ඒතේව බහුතරා සත්තා යේ බීජගාමභූතගාමසමාරම්භා අප්පටිවිරතා ....(පෙ).... යෝගෝ කරණීයෝති.",
  "sinhala": "එසෙයින් ම මහණෙනි, යම් සත්වයෝ ගස් කොළන් සිඳලීමෙන් වැළකී සිටිත් නම්, ඔවුහු අල්ප වෙති. එසේ නමුත් යම් සත්වයෝ ගස් කොළන් සිඳලීමෙන් නොවැළකී සිටිත් නම්, ඔවුහු ම ඉතාමත් බොහෝ ය. ....(පෙ).... මෙය දුක් නිරුද්ධවන්නා වූ මාර්ගය යැයි අවබෝධ කරනු පිණිස වීර්යය කළ යුත්තේ ය.",
  "ai_short_intro": "සත්වයා කෙරෙහි කරුණාවෙන් යුතුව ජීවිතය පවත්වාගෙන යාමේ වැදගත්කම"
}