{
  "nikaya": "සගාථ වග්ගෝ",
  "vagga": "11.1.6. කුලාවක සුත්තං",
  "sutta_title": "11.1.6. කැදැල්ල ගැන වදාළ දෙසුම",
  "description": "",
  "pali": "සාවත්‌ථියං..... භූතපුබ්‌බං භික්ඛවේ දේවාසුරසංගාමෝ සමුපබ්බූළ්හෝ අහෝසි. තස්‌මිං ඛෝ පන භික්ඛවේ සංගාමේ අසුරා ජිනිංසු. දේවා පරාජිංසු. පරාජිතා ච ඛෝ භික්ඛවේ දේවා අපායංස්‌වේව උත්‌තරේනමුඛා, අභියංස්‌වේව නේ අසුරා. අථ ඛෝ භික්ඛවේ සක්කෝ දේවානමින්‌දෝ මාතලී සංගාහකං ගාථාය අජ්‌ඣභාසි. ඒවං භද්‌දන්‌තවාති ඛෝ භික්ඛවේ මාතලි සං‌ගාහකෝ සක්‌කස්‌ස දේවානමින්දස්ස පටිස්‌සුත්‌වා සහස්‌සයුත්‌තං ආජඤ්‌ඤරථං පච්‌චුදාවත්‌තේසි. අථ ඛෝ භික්ඛවේ අසුරානං ඒතදහෝසි. පච්‌චුදාවත්‌තෝ ඛෝ දානි සක්‌කස්‌ස දේවානමින්දස්ස සහස්‌සයුත්‌තෝ ආජඤ්‌ඤරථෝ. දුතියම්‌පි ඛෝ දේවා අසුරේහි සංගාමෙස්‌සන්‌තීති භීතා අසුරපුරමේව පාවිසිංසු. ඉති ඛෝ භික්ඛවේ සක්‌කස්‌ස දේවානමින්දස්ස ධම්මේනේව ජයෝ අහෝසි.",
  "sinhala": "සැවැත් නුවර ..... මහණෙනි, මෙය පෙර සිදුවූ දෙයකි. දෙවියන් හා අසුරයන් අතර යුද්ධයක්\nඑළඹ සිටියේය. මහණෙනි, ඒ යුද්ධයෙහිදී අසුරයෝ දිනුවාහුය. දෙවියෝ\nපැරදුනාහුය. ඉක්බිති මහණෙනි, පරාජිත දෙවියෝ උතුරු දිශාව බලා පලාගියෝ ම ය.\nඅසුරයෝ පලායන ඔවුන් ලුහුබැඳ ගියෝ ම ය. මහණෙනි, එකල්හි සක්දෙවිඳු\nතෙමේ මාතලී රියදුරු හට ගාථාවෙන් මෙය කීය. “මාතලී, හිඹුල් වනයෙහි ගුරුලන්ගේ කැදලි ඇත්තාහ. ඒවා මගහැර\nරියහිසින් බැහැර වෙව. ඒකාන්තයෙන් ම අසුරයන් උදෙසා ප්‍රාණය\nඅත්හරිමි. මේ ගුරුල්ලෝ නැසුණු කැදලි ඇත්තෝ නොවෙත්වා!” මහණෙනි, “එසේය, නුඹවහන්සේට සෙත් වේවා” කියා මාතලී රියදුරු\nතෙමේ සක්දෙවිඳුට පිළිවදන් දී ආජානීය අසුන් දහසකින් යුතු රථය කරකවා\nහැරවීය. එකල්හි මහණෙනි, අසුරයන්ට මේ අදහස ඇතිවිය. “දැන් සක්දෙවිඳුගේ\nආජානීය අසුන් දහසකින් යුතු රථය කරකවා හැරවීය. නැවත වතාවක් දෙවියෝ\nඅසුරයන් හා යුද කරන්ට එන්නාහු යැ’ යි භීතිය පත්ව අසුරපුරයට ම පිවිසියාහුය. මෙසේ මහණෙනි, සක් දෙවිඳුහට ධර්මයෙන් ම ජය අත්වූයේය.",
  "ai_short_intro": "ධර්ම බලයෙන් අකුසල බලයන් ජයග්‍රහණය කිරීමේ ස්වභාවය"
}