{
  "nikaya": "නිදාන වග්ගෝ",
  "vagga": "1.8.1. ජරා මරණ සුත්තං",
  "sutta_title": "1.8.1. ජරා මරණ ගැන වදාළ දෙසුම",
  "description": "",
  "pali": "ඒවං මේ සුතං. ඒකං සමයං භගවා සාවත්‌ථියං විහරති ජේතවනේ අනාථපිණ්‌ඩිකස්‌ස ආරාමේ. තත්‍ර ඛෝ භගවා ....(පෙ).... ඒතදවෝච. යේ හි කේචි භික්ඛවේ, සමණා වා බ්‍රාහ්‌මණා වා ජරාමරණං නප්‌පජානන්‌ති, ජරාමරණසමුදයං නප්‌පජානන්‌ති, ජරාමරණනිරෝධං නප්‌පජානන්‌ති, ජරාමරණනිරෝධගාමිනිං පටිපදං නප්‌පජානන්‌ති. න මේ තේ භික්ඛවේ, සමණා වා බ්‍රාහ්‌මණා වා සමණේසු වා සමණසම්‌මතා, බ්‍රාහ්‌මණේසු වා බ්‍රාහ්‌මණසම්‌මතා, න ච පන තේ ආයස්‌මන්‌තෝ සාමඤ්‌ඤත්‌ථං වා බ්‍රහ්‌මඤ්‌ඤත්‌ථං වා දිට්ඨේව ධම්මේ සයං අභිඤ්‌ඤා සච්‌ඡිකත්‌වා උපසම්‌පජ්‌ජ විහරන්‌ති. යේ ච ඛෝ කේචි භික්ඛවේ, සමණා වා බ්‍රාහ්‌මණා වා ජරාමරණං පජානන්‌ති, ජරාමරණසමුදයං පජානන්‌ති, ජරාමරණනිරෝධං පජානන්‌ති, ජරාමරණනිරෝධගාමිනිං පටිපදං පජානන්‌ති. තේ ඛෝ මේ භික්ඛවේ, සමණා වා බ්‍රාහ්‌මණා වා සමණේසු චේව සමණසම්‌මතා, බ්‍රාහ්‌මණේසු ච බ්‍රාහ්‌මණසම්‌මතා. තේ ච පනායස්‌මන්‌තෝ සාමඤ්‌ඤත්‌ථඤ්‌ච බ්‍රහ්‌මඤ්‌ඤත්‌ථඤ්‌ච දිට්ඨේව ධම්මේ සයං අභිඤ්‌ඤා සච්‌ඡිකත්‌වා උපසම්‌පජ්‌ජ විහරන්‌තී’ති.",
  "sinhala": "මා හට අසන්නට ලැබුණේ මේ විදිහටයි. ඒ දිනවල භාග්‍යවතුන් වහන්සේ වැඩසිටියේ සැවැත් නුවර ජේතවනය නම් වූ අනේපිඬු සිටුතුමාගේ ආරාමයේය. එදා භාග්‍යවතුන් වහන්සේ ....(පෙ).... මෙම දේශනය වදාළා. පින්වත් මහණෙනි, යම්කිසි ශ්‍රමණයන් වේවා, බ්‍රාහ්මණයන් වේවා, ජරා මරණ ගැන අවබෝධයක් නැත්නම්, ජරා මරණ හටගැනීම ගැන අවබෝධයක් නැත්නම්, ජරා මරණ නිරුද්ධ වීම ගැන අවබෝධයක් නැත්නම්, ජරා මරණ නිරුද්ධ වීම පිණිස පවතින ප්‍රතිපදාව ගැන අවබෝධයක් නැත්නම්, පින්වත් මහණෙනි, ඒ ශ්‍රමණයන් වේවා, බ්‍රාහ්මණයන් වේවා සැබෑම ශ්‍රමණයන් අතර ශ්‍රමණයන් බවට සම්මත වෙන්නේ නෑ. සැබෑම බ්‍රාහ්මණයන් අතර බ්‍රාහ්මණයන් බවට සම්මත වෙන්නේ නෑ. ඒ ආයුෂ්මත්වරුන්ට ශ්‍රමණ ජීවිතයේ ප්‍රතිඵලයක් හෝ බ්‍රාහ්මණ ජීවිතයේ ප්‍රතිඵලයක් හෝ මේ ජීවිතය තුළ නම් තමන්ගේම අවබෝධ ඤාණයෙන් සාක්ෂාත් කරගෙන වාසය කරන්න ලැබෙන්නේ නෑ. පින්වත් මහණෙනි, යම්කිසි ශ්‍රමණයන් වේවා, බ්‍රාහ්මණයන් වේවා, ජරා මරණ ගැන අවබෝධයක් තියෙනවා නම්, ජරා මරණ හටගැනීම ගැන අවබෝධයක් තියෙනවා නම්, ජරා මරණ නිරුද්ධ වීම ගැන අවබෝධයක් තියෙනවා නම්, ජරා මරණ නිරුද්ධ වීම පිණිස පවතින ප්‍රතිපදාව ගැන අවබෝධයක් තියෙනවා නම්, පින්වත් මහණෙනි, ඒ ශ්‍රමණයන් වේවා, බ්‍රාහ්මණයන් වේවා සැබෑම ශ්‍රමණයන් අතර ශ්‍රමණයන් බවට සම්මත වෙනවා. සැබෑම බ්‍රාහ්මණයන් අතර බ්‍රාහ්මණයන් බවට සම්මත වෙනවා. ඒ ආයුෂ්මත්වරුන්ට ශ්‍රමණ ජීවිතයේ ප්‍රතිඵලයක් හෝ බ්‍රාහ්මණ ජීවිතයේ ප්‍රතිඵලයක් හෝ මේ ජීවිතය තුළ තමන්ගේම අවබෝධ ඤාණයෙන් සාක්ෂාත් කරගෙන වාසය කරන්න ලැබෙනවා.",
  "ai_short_intro": "ජරා මරණ පිළිබඳ නිවැරදි අවබෝධය තුළින් සැබෑ ශ්‍රමණ භාවය සහ බ්‍රාහ්මණ භාවය සාක්ෂාත් කරගැනීම",
  "ai_detailed_summary": "සැබෑ ශ්‍රමණයෙකු හෝ බ්‍රාහ්මණයෙකු ලෙස සම්මත වීමට නම් ජරා මරණය, ජරා මරණය හටගැනීම, ජරා මරණය නිරුද්ධ වීම සහ ජරා මරණය නිරුද්ධ කිරීමේ ප්‍රතිපදාව පිළිබඳව පූර්ණ අවබෝධයක් තිබිය යුතුය. මෙම මූලික ධර්ම කරුණු පිළිබඳව"
}