{
  "nikaya": "මහා වග්ගෝ",
  "vagga": "1.10.1. පාචීනනින්න සුත්තං",
  "sutta_title": "1.10.1. පෙරදිගට නැමී තිබීම ගැන වදාළ දෙසුම",
  "description": "",
  "pali": "සෙය්‍යථාපි භික්ඛවේ, ගංගා නදී පාචීනනින්නා පාචීනපෝණා පාචීනපබ්භාරා. ඒවමේව ඛෝ භික්ඛවේ, භික්ඛු අරියං අට්ඨංගිකං මග්ගං භාවෙන්තෝ අරියං අට්ඨංගිකං මග්ගං බහුලීකරොන්තෝ නිබ්බානනින්නෝ හෝති නිබ්බානපෝණෝ නිබ්බානපබ්භාරෝ. කථඤ්ච භික්ඛවේ, භික්ඛු අරියං අට්ඨංගිකං මග්ගං භාවෙන්තෝ අරියං අට්ඨංගිකං මග්ගං බහුලීකරොන්තෝ නිබ්බානනින්නෝ හෝති නිබ්බානපෝණෝ නිබ්බානපබ්භාරෝ. ඉධ භික්ඛවේ, භික්ඛු සම්මාදිට්ඨිං භාවේති රාගවිනයපරියෝසානං දෝසවිනයපරියෝසානං මෝහවිනයපරියෝසානං ....(පෙ).... සම්මාසමාධිං භාවේති රාගවිනයපරියෝසානං දෝසවිනයපරියෝසානං මෝහවිනයපරියෝසානං. ඒවං ඛෝ භික්ඛවේ, භික්ඛු අරියං අට්ඨංගිකං මග්ගං භාවෙන්තෝ අරියං අට්ඨංගිකං මග්ගං බහුලීකරොන්තෝ නිබ්බානනින්නෝ හෝති නිබ්බානපෝණෝ නිබ්බානපබ්භාරෝති.",
  "sinhala": "මහණෙනි, ගංගා නදිය පෙරදිගට නැමී, පෙරදිගට නැඹුරු වී, පෙරදිගට බර වී ඇත්තේ යම් සේ ද, එසෙයින් ම මහණෙනි, ආර්ය අෂ්ටාංගික මාර්ගය දියුණු කරන්නා වූ, ආර්ය අෂ්ටාංගික මාර්ගය බහුල ව ප්‍රගුණ කරන්නා වූ භික්ෂුව නිවනට නැමුණේ වෙයි. නිවනට නැඹුරු වූයේ වෙයි. නිවනට බර වූයේ වෙයි. මහණෙනි, භික්ෂුවක් නිවනට නැමී සිටින්නේ, නිවනට නැඹුරු වන්නේ, නිවනට බර වන්නේ, කුමන අයුරින් ආර්ය අෂ්ටාංගික මාර්ගය දියුණු කරන විට ද? කුමන අයුරින් ආර්ය අෂ්ටාංගික මාර්ගය බහුල ව ප්‍රගුණ කරන විට ද? මහණෙනි, මෙහිලා භික්ෂුව රාගය දුරු කිරීම අවසානය කොට ගෙන, ද්වේෂය දුරු කිරීම අවසානය කොට ගෙන, මෝහය දුරු කිරීම අවසානය කොට ගෙන නිවැරදි දෘෂ්ටිය දියුණු කරයි. ….(පෙ)…. රාගය දුරු කිරීම අවසානය කොට ගෙන, ද්වේෂය දුරු කිරීම අවසානය කොට ගෙන, මෝහය දුරු කිරීම අවසානය කොට ගෙන නිවැරදි චිත්තේකාග්‍රතාවය දියුණු කරයි. මහණෙනි, භික්ෂුවක් නිවනට නැමී සිටින්නේ, නිවනට නැඹුරු වන්නේ, නිවනට බර වන්නේ, මේ අයුරින් ආර්ය අෂ්ටාංගික මාර්ගය දියුණු කරන විට ය. මේ අයුරින් ආර්ය අෂ්ටාංගික මාර්ගය බහුල ව ප්‍රගුණ කරන විට ය.",
  "ai_short_intro": "ආර්ය අෂ්ටාංගික මාර්ගය ප්‍රගුණ කිරීම තුළින් මෝහය, රාගය, ද්වේෂය දුරලමින් නිවන සාක්ෂාත් කරගැනීම",
  "ai_detailed_summary": "ගංගා නදිය පෙරදිගට නැමීම මෙන්, ආර්ය අෂ්ටාංගික මාර්ගය ප්‍රගුණ කරන භික්ෂුවක් නිවන වෙත නැඹුරු වීම සහ බර වීම සිදුවේ.\n\nමෙම භික්ෂුව නිවන වෙත නැඹුරු වන්නේ, ආර්ය අෂ්ටාංගික මාර්ගය දියුණු කිරීමේ ක්‍රියාවලිය තුළිනි. එම ක්‍රියාවලියේදී, පළමුව රාගය දුරු කිරීම අවසානයට ගෙන යනු ලැබේ. ඉන්පසුව, ද්වේෂය දුරු කිරීම අවසානයට ගෙන යනු ලැබේ. ඊට පසුව, මෝහය දුරු කිරීම අවසානයට ගෙන යනු ලැබේ. මෙම අනුපිළිවෙලින්, භික්ෂුව නිවැරදි දෘෂ්ටිය දියුණු කරයි.\n\nතවද, මෙම ක්‍රියාවලිය තුළදී, රාගය, ද්වේෂය සහ මෝහය යන සංස්කාරයන් දුරු කිරීමෙන් පසු, භික්ෂුව නිවැරදි චිත්තේකාග්‍රතාවය දියුණු කරයි.\n\nඑබැවින්, භික්ෂුවක් නිවනට නැමී සිටින්නේ, මෙම ආකාරයටම ආර්ය අෂ්ටාංගික මාර්ගය ක්‍රමානුකූලව දියුණු කරමින්, රාගය, ද්වේෂය, මෝහය යන සංස්කාරයන් දුරු කරමින්, අනුපිළිවෙලට නිවැරදි දෘෂ්ටිය සහ නිවැරදි චිත්තේකාග්‍රතාවය වර්ධනය කරගනිමින් ය."
}