{
  "nikaya": "සළායතන වග්ගෝ",
  "vagga": "7.1.10. ගිලාන සුත්තං",
  "sutta_title": "7.1.10. ගිලන් වූ චිත්ත ගෘහපති පිළිබඳ දෙසුම",
  "description": "",
  "pali": "තේන ඛෝ පන සමයේන චිත්තෝ ගහපති ආබාධිකෝ හෝති දුක්ඛිතෝ බාළ්හගිලානෝ. අථ ඛෝ සම්බහුලා ආරාමදේවතා වනදේවතා රුක්ඛදේවතා ඕසධි තිණ වනස්පතීසු අධිවත්ථා දේවතා සංගම්ම සමාගම්ම චිත්තං ගහපතිං ඒතදවෝචුං: පණිධේහි ගහපති අනාගතමද්ධානං රාජා අස්සං චක්කවත්තීති. ඒවං වුත්තේ චිත්තෝ ගහපති තා ආරාමදේවතා වනදේවතා රුක්ඛදේවතා ඕසධී තිණ වනස්පතීසු අධිවත්ථා දේවතා ඒතදවෝච: ‘තම්පි අනිච්චං, තම්පි අද්ධුවං තම්පි පහාය ගමනීයන්ති’. ඒවං වුත්තේ චිත්තස්ස ගහපතිනෝ මිත්තාමච්චා ඤාතිසාලෝහිතා චිත්තං ගහපතිං ඒතදවෝචුං: ‘සතිං අය්‍යපුත්ත උපට්ඨපේහි මා විප්පලපී’ති. කින්නාහං වදාමි යං මං තුම්හේ ඒවං වදේථ: ‘සතිං අය්‍යපුත්ත උපට්ඨපේහි මා විප්පලපී’ති. ඒවං ඛෝ ත්වං අය්‍යපුත්ත වදේසි: “තම්පි අනිච්චං තම්පි අද්ධුවං තම්පි පහාය ගමනීය’න්ති. තථා හි පන මං ආරාමදේවතා වනදේවතා රුක්ඛදේවතා ඕසධි තිණ වනස්පතීසු අධිවත්ථා දේවතා ඒවමාහංසු: ‘පණිධේහි ගහපති අනාගතමද්ධානං රාජා අස්සං චක්කවත්තී’ති. තාසාහං ඒවං වදාමි: තම්පි අනිච්චං තම්පි අද්ධුවං තම්පි පහාය ගමනීයන්ති. කින්තේ අය්‍යපුත්ත ආරාමදේවතා වනදේවතා රුක්ඛදේවතා ඕසධී තිණ වනස්පතීසු අධිවත්ථා දේවතා අත්ථවසං සම්පස්සමානා ඒවමාහංසු: පණිධේහි ගහපති අනාගතමද්ධානං රාජා අස්සං චක්කවත්තීති. තාසං ඛෝ ආරාමදේවතානං වනදේවතානං රුක්ඛදේවතානං ඕසධී තිණ වනස්පතීසු අධිවත්ථානං දේවතානං ඒවං හෝති: අයං ඛෝ චිත්තෝ ගහපති සීලවා කල්‍යාණධම්මෝ. සචේ පණිදහිස්සති අනාගතමද්ධානං රාජා අස්සං චක්කවත්තීති, ඉජ්ඣිස්සති සීලවතෝ චේතෝපණිධි, විසුද්ධත්තා සීලස්ස, ධම්මිකෝ ධම්මරාජා ධම්මිකං බලිං අනුප්පදස්සතීති. ඉමං ඛෝ ආරාමදේවතා වනදේවතා රුක්ඛදේවතා ඕසධිතිණවනස්පතීසු අධිවත්ථා දේවතා අත්ථවසං සම්පස්සමානා ඒවමාහංසු: ‘පණිධේහි ගහපති අනාගතමද්ධානං රාජා අස්සං චක්කවත්තී’ති. තාසාහං ඒවං වදාමි: ‘තම්පි අනිච්චං තම්පි අද්ධුවං තම්පි පහාය ගමනීය’න්ති. තේන හි අය්‍යපුත්ත අම්හේපි ඕවදේහීති. තස්මාතිහ වෝ ඒවං සික්ඛිතබ්බං: බුද්ධේ අවෙච්චප්පසාදේන සමන්නාගතා භවිස්සාම, ඉතිපි සෝ භගවා අරහං සම්මා සම්බුද්ධෝ විජ්ජාචරණසම්පන්නෝ සුගතෝ ලෝකවිදූ අනුත්තරෝ පුරිසදම්මසාරථි සත්ථා දේවමනුස්සානං බුද්ධෝ භගවාති. ධම්මේ අවෙච්චප්පසාදේන සමන්නාගතා භවිස්සාම: ස්වාක්ඛාතෝ භගවතා ධම්මෝ සන්දිට්ඨිකෝ අකාලිකෝ ඒහිපස්සිකෝ ඕපනයිකෝ පච්චත්තං වේදිතබ්බෝ විඤ්ඤූහීති. සංඝේ අවෙච්චප්පසාදේන සමන්නාගතා භවිස්සාම: සුපටිපන්නෝ භගවතෝ සාවකසංඝෝ, උජුපටිපන්නෝ භගවතෝ සාවකසංඝෝ, ඤායපටිපන්නෝ භගවතෝ සාවකසංඝෝ, සාමීචිපටිපන්නෝ භගවතෝ සාවකසංඝෝ, යදිදං චත්තාරි පුරිසයුගානි අට්ඨපුරිසපුග්ගලා ඒස භගවතෝ සාවකසංඝෝ ආහුනෙය්‍යෝ පාහුනෙය්‍යෝ දක්ඛිණෙය්‍යෝ අඤ්ජලිකරණීයෝ අනුත්තරං පුඤ්ඤක්ඛෙත්තං ලෝකස්සාති. යං ඛෝ පන කිඤ්චි කුලේ දෙය්‍යධම්මං සබ්බන්තං අප්පටිවිභත්තං භවිස්සති සීලවන්තේහි කල්‍යාණධම්මේහීති. ඒවං හි වෝ සික්ඛිතබ්බන්ති. අථ ඛෝ චිත්තෝ ගහපති මිත්තාමච්චේ ඤාතිසාලෝහිතේ බුද්ධේ ච ධම්මේ ච සංඝේ ච පසාදේ චාගේ ච සමාදපෙත්වා කාලමකාසීති. තත්‍රැද්දානං:",
  "sinhala": "ඒ දිනවල චිත්ත ගෘහපතිතුමා අසනීප වෙලා, දුකට පැමිණිලා, බලවත්ව ගිලන් වෙලා හිටියා. එතකොට බොහෝ ආරාමවාසී දෙවිවරු, වන දේවතාවරු, රුක්දේවතාවරු, ඖෂධ, තණ, සුවිසල් රුක් වලට අරක්ගත් දෙවිවරු රැස් වෙවී, චිත්ත ගෘහපතිතුමාට මෙහෙම කිව්වා. “පින්වත් ගෘහපතිතුමනි, අනාගතයෙහි සක්විති රජෙකු වන්නට සිත පිහිටුවාගත මැනැව” කියලා. එතකොට චිත්ත ගෘහපතිතුමා ඒ ආරාමවාසී දෙවිවරුන්ට, වන දේවතාවරුන්ට, රුක්දේවතාවරුන්ට, ඖෂධ, තණ, සුවිසල් රුක් වලට අරක්ගත් දෙවිවරුන්ට මෙහෙම කිව්වා. “ඒකත් අනිත්‍යයි. ඒකත් අස්ථිරයි. ඒවත් අතහැරලා යා යුතුයි නොවැ” කියලා. එසේ කී විට චිත්ත ගෘහපතියාගේ යහළු මිතුරන්, නෑදෑයින්, ලේ ඤාතීන් චිත්ත ගෘහපතිතුමාට මෙහෙම කිව්වා. “ආර්ය පුත්‍රයෙනි, සිහිය පිහිටුවාගත මැනැව. නිකරුණේ නොදොඩනු මැනැව” කියලා. “මං ඔබලාට කුමක් කියලද ඔබලා මට ‘ආර්ය පුත්‍රයෙනි, සිහිය පිහිටුවාගත මැනැව. නිකරුණේ නොදොඩනු මැනැව’ කියලා කියන්නේ?” “ආර්ය පුත්‍රයෙනි, ඔබ මෙහෙම කිව්වා නොවැ. ‘ඒකත් අනිත්‍යයි. ඒකත් අස්ථිරයි. ඒවත් අතහැරලා යා යුතුයි නොවැ’ කියලා.” “ඒක ඇත්ත. ආරාමවාසී දෙවිවරු, වන දේවතාවරු, රුක්දේවතාවරු, ඖෂධ, තණ, සුවිසල් රුක්වලට අරක්ගත් දෙවිවරු රැස්වෙවී මට මෙහෙම කිව්වා. ‘පින්වත් ගෘහපතිතුමනි, අනාගතයෙහි සක්විති රජෙකු වන්නට සිත පිහිටුවාගත මැනැව’ කියලා. මං ඔවුන්ටයි මෙහෙම කියන්නේ. ‘ඒකත් අනිත්‍යයි. ඒකත් අස්ථිරයි. ඒවත් අතහැරලා යා යුතුයි නොවැ’ කියලා.” “ආර්ය පුත්‍රයෙනි, ඒ ආරාමවාසී දෙවිවරු, වන දේවතාවරු, රුක්දේවතාවරු, ඖෂධ, තණ, සුවිසල් රුක්වලට අරක්ගත් දෙවිවරු රැස්වෙවී ‘පින්වත් ගෘහපතිතුමනි, අනාගතයෙහි සක්විති රජෙකු වන්නට සිත පිහිටුවාගත මැනැව’ කියලා ඔය විදිහට කිව්වේ කවර ප්‍රයෝජනයක් දැකල ද?” “ඒ ආරාමවාසී දෙවිවරුන්ට, වන දේවතාවරුන්ට, රුක්දේවතාවරුන්ට, ඖෂධ, තණ, සුවිසල් රුක් වලට අරක්ගත් දෙවිවරුන්ට මේ විදිහට හිතෙනවා. ‘මේ චිත්ත ගෘහපතිතුමා සිල්වත්, කල්‍යාණ ධර්මයන්ගෙන් යුක්තයි. ඉදින් අනාගතයෙහි සක්විති රජ කෙනෙක් වෙමියි චේතනාව පිහිටුවා ගන්නේ නම්, සිල්වත් කෙනෙකුගේ ඒ චිත්ත ප්‍රාර්ථනය පිරිසිදු සීලයක් තියෙන නිසා සමෘද්ධිමත් වෙනවා. ධාර්මික වූ දහම් රජු, ධාර්මිකව පුද පූජාවල් පවත්වනවා.’ ඒ කරුණ දකිමින් තමයි ඒ ආරාමවාසී දෙවිවරු, වන දේවතාවරු, රුක්දේවතාවරු, ඖෂධ, තණ, සුවිසල් රුක් වලට අරක්ගත් දෙවිවරු රැස්වෙවී මට මෙහෙම කිව්වේ. ‘පින්වත් ගෘහපතිතුමනි, අනාගතයෙහි සක්විති රජෙකු වන්නට සිත පිහිටුවාගත මැනැව’ කියලා. ඔවුන්ට තමයි මං ඒ විදිහට කිව්වේ. ‘ඒකත් අනිත්‍යයි. ඒකත් අස්ථිරයි. ඒවත් අතහැරලා යා යුතුයි නොවැ’ කියලා.” “එසේ වී නම් ආර්ය පුත්‍රය, අපටත් අවවාද කළ මැනැව.” “එහෙනම් ඔබලා මේ අයුරින් හික්මිය යුතුයි. මේ මේ අයුරින් ඒ භාග්‍යවතුන් වහන්සේ අරහං වන සේක, සම්මා සම්බුද්ධ වන සේක, විජ්ජාචරණ සම්පන්න වන සේක, සුගත වන සේක, ලෝකවිදූ වන සේක, අනුත්තරෝ පුරිසදම්ම සාරථී වන සේක, සත්ථා දේවමනුස්සානං වන සේක, බුද්ධ වන සේක, භගවා වන සේක කියලා බුදුරජාණන් වහන්සේ කෙරෙහි නොසෙල්වෙන ලෙස පැහැදීම ඇති අය වෙනවා. මේ අයුරින් ඒ භාග්‍යවතුන් වහන්සේ විසින් වදාරණ ලද ශ්‍රී සද්ධර්මය ස්වාක්ඛාත වන සේක, සන්දිට්ඨික වන සේක, අකාලික වන සේක, ඒහිපස්සික වන සේක, ඕපනයික වන සේක, පච්චත්තං වේදිතබ්බෝ විඤ්ඤූහි වන සේක කියලා ශ්‍රී සද්ධර්මය කෙරෙහි නොසෙල්වෙන ලෙස පැහැදීම ඇති අය වෙනවා. මේ අයුරින් ඒ භාග්‍යවතුන් වහන්සේගේ ශ්‍රාවක සංඝ රත්නය සුපටිපන්න වන සේක, භාග්‍යවතුන් වහන්සේගේ ශ්‍රාවක සංඝ රත්නය උජුපටිපන්න වන සේක, භාග්‍යවතුන් වහන්සේගේ ශ්‍රාවක සංඝ රත්නය ඤායපටිපන්න වන සේක, භාග්‍යවතුන් වහන්සේගේ ශ්‍රාවක සංඝ රත්නය සාමීචිපටිපන්න වන සේක, භාග්‍යවතුන් වහන්සේගේ ශ්‍රාවක සංඝ රත්නය පුරුෂ යුගල වශයෙන් සතරක් ද, පුරුෂ පුද්ගල වශයෙන් අට දෙනෙක් ද වන සේක, භාග්‍යවතුන් වහන්සේගේ ශ්‍රාවක සංඝ රත්නය ආහුනෙය්‍ය වන සේක, පාහුනෙය්‍ය වන සේක, දක්ඛිණෙය්‍ය වන සේක, අංජලිකරණීය වන සේක, ලොවට උතුම් පින්කෙත වන සේක කියලා ආර්ය ශ්‍රාවක සංඝ රත්නය කෙරෙහි නොසෙල්වෙන ලෙස පැහැදීම ඇති අය වෙනවා. ඒ වගේම මේ පවුල්වල දාන විෂයෙහි දිය යුතු යමක් ඇත්නම්, ඒ සියල්ල සිල්වත් වූ කල්‍යාණ ධර්ම ඇති උතුමන් හා තෝරා බේරා නො බෙදා දීම වන්නේය කියා ඔය අයුරින්ය ඔබලා හික්මිය යුත්තේ.” ඉතින් චිත්ත ගෘහපතිතුමා යහළු මිතුරන්ව නෑදෑ ලේ ඤාතීන්ව බුදුරජාණන් වහන්සේ කෙරෙහිත්, ශ්‍රී සද්ධර්මය කෙරෙහිත්, ආර්ය සංඝයා කෙරෙහිත් ප්‍රසාදයෙහි පිහිටුවලා, ත්‍යාගයෙහිත් සමාදන් කරවලා කළුරිය කළා. එහි පිළිවෙළ උද්දානය යි. සංයෝජන සූත්‍රය, ඉසිදත්ත සූත්‍ර දෙක, මහක සූත්‍රය, කාමභූ සූත්‍ර දෙක, ගෝදත්ත සූත්‍රය, නිගණ්ඨ සූත්‍රය, අචේල සූත්‍රය, ගිලාන සූත්‍රය යන දෙසුම් වලින් මෙම සංයුක්තය සමන්විත වෙයි.",
  "ai_short_intro": "අනිත්‍යතාවය අවබෝධ කර ගැනීම තුළින් බුදුරජාණන් වහන්සේගේ ධර්මයට සහ සංඝරත්නයට ඇති විශ්වාසය වර්ධනය කිරීම",
  "ai_detailed_summary": "අසනීපයෙන් හා දැඩි දුකෙන් පීඩිතව සිටි චිත්ත ගෘහපතිතුමා වෙත ආරාමවාසී, වන, රුක්, ඖෂධ, තණ සහ සුවිසල් රුක් ආශ්‍රිත දෙවිවරුන් රැස්වී, ඔහුගේ පින්වත් බව හා සීලවත් බව අගය කරමින්, අනාගතයේදී සක්විති රජෙකු වීමේ ප්‍රාර්ථනාව සිදු කරන ලෙස උපදෙස් ලබා දෙති. එහෙත් චිත්ත ගෘහපතිතුමා එම ලෞකික උත්තරීතරත්වය ද අනිත්‍ය හා අස්ථිර බවත්, එබැවින් එය ද අතහැර දැමිය යුතු බවත් පවසමින් එම ප්‍රාර්ථනාව ප්‍රතික්ෂේප කරයි.\n\nමෙම අවස්ථාවේදී චිත්ත ගෘහපතිතුමාගේ යහළු මිතුරන් හා නෑදෑයින් ඔහුට සිහියෙන් යුතුව කටයුතු කරන ලෙස අවවාද කරන අතර, ගෘහපතිතුමා තමන් එම දෙවිවරුන්ගේ උපදෙස් අනුගමනය කරමින් ලෞකික සැප සම්පත් පිළිබඳ අනිත්‍යතාවය අවබෝධ කරගත් බව පැහැදිලි කරයි. දෙවිවරුන් මෙලෙස ප්‍රාර්ථනා කළේ ඔහුගේ පිරිසිදු සීලය හා ධාර්මික බව නිසා එම ප්‍රාර්ථනාව සාර්ථක වනු ඇතැයි යන චේතනාවෙන් බව ද ඔහු පවසයි.\n\nඅවසානයේදී, සියලු ලෞකික ප්‍රාර්ථනා අතහැර දමා බුද්ධ, ධර්ම, සංඝ යන තෙරුවන් කෙරෙහි නොසෙල්වෙන ශ්‍රද්ධාව ඇති කරගත යුතු ආකාරයත්, ශ්‍රී සද්ධර්මයේ සත්‍යතාවය අවබෝධ කරගත යුතු ආකාරයත්, ආර්ය ශ්‍රාවක සංඝ රත්නයේ උත්තම ගුණාංග හා පින්කෙතක් වීමේ උතුම් බව වටහාගත යුතු ආකාරයත් පිළිබඳව ගෘහපතිතුමා සිය නෑදෑයන් හා මිතුරන්ව ද අවවාද කරයි. එසේම, දානමය කටයුතුවලදී සිල්වත් උතුමන් හට දානය පිරිනැමීමෙහි ඇති වැදගත්කම ද ඔහු පෙන්වා දෙයි. චිත්ත ගෘහපතිතුමා සිය සියලු හිතවතුන් තෙරුවන් කෙරෙහි ප්‍රසාදයෙහි හා ත්‍යාගයෙහි පිහිටුවමින් සිය ජීවිතය නිම කළේය."
}