{
  "nikaya": "දසක නිපාතෝ",
  "vagga": "10.1.5.9. සරීරට්ඨධම්ම සුත්තං",
  "sutta_title": "10.1.5.9. සිරුරෙහි ඇති දේ ගැන වදාළ දෙසුම",
  "description": "",
  "pali": "(සාවත්ථි) දස ඉමේ භික්ඛවේ ධම්මා සරීරට්ඨා, කතමේ දස: සීතං, උණ්හං, ජිඝච්ඡා, පිපාසා, උච්චාරෝ, පස්සාවෝ, කායසංවරෝ, වචීසංවරෝ, ආජීවසංවරෝ, පෝනෝභවිකෝ භවසංඛාරෝ. ඉමේ ඛෝ භික්ඛවේ දස ධම්මා සරීරට්ඨා ති.",
  "sinhala": "සැවැත් නුවර දී ය ……….. “මහණෙනි, සිරුරෙහි පිහිටා ඇති මේ කරුණු දසයෙකි. කවර දසයක් ද යත්; සීතල ය. උණුසුම ය. කුසගින්න ය. පිපාසය ය. අසුචි ය. මුත්‍ර ය. කාය සංවරය ය. වාක් සංවරය ය. ආජීව සංවරය ය. යළි භවය සකසන භව සංස්කාරය ය. මහණෙනි, සිරුරෙහි පිහිටා ඇති කරුණු දසය නම් මේවා ය.",
  "ai_short_intro": "ශරීරය තුළ පවතින දහ ආකාරයේ සංස්කාරයන් පිළිබඳ විස්තරය"
}