{
  "nikaya": "තික නිපාතෝ",
  "vagga": "3.3.5.4.",
  "sutta_title": "",
  "description": "",
  "pali": "47. තීහි භික්ඛවේ ධම්මේහි සමන්නාගතෝ ....(පෙ).... ඒවං නිරයේ. කතමේහි තීහි? අසුචිනා කාය කම්මේන, අසුචිනා වචීකම්මේන, ....(පෙ).... මනෝකම්මේන. ඉමේහි ඛෝ තීහි ....(පෙ).... එවං නිරයේ. තීහි භික්ඛවේ ....(පෙ).... එවං සග්ගේ. කතමේහි තීහි? සුචිනා කායකම්මේන, සුචිනා වචීකම්මේන ....(පෙ).... මනෝකම්මේන. ඉමේහි ඛෝ භික්ඛවේ, තීහි ධම්මේහි සමන්නාගතෝ යථාභතං නික්ඛිත්තෝ ඒවං සග්ගේති.",
  "sinhala": "47. පින්වත් මහණෙනි, කරුණු තුනකින් යුක්ත වූ කෙනා ....(පෙ).... ඒ අයුරින්ම නිරයේ උපදිනවා. කවර කරුණු තුනකින්ද?  අපිරිසිදු කාය කර්මයෙන්, අපිරිසිදු වචී කර්මයෙන් හා අපිරිසිදු මනෝ කර්මයෙන්ය. පින්වත් මහණෙනි, මේ කරුණු තුනෙන් ....(පෙ).... ඒ අයුරින්ම නිරයේ උපදිනවා.  පින්වත් මහණෙනි, කරුණු තුනකින් ....(පෙ).... ඒ අයුරින්ම සුගතියේ උපදිනවා. කවර කරුණු තුනකින්ද?  පිරිසිදු වූ කාය කර්මයෙන්, පිරිසිදු වූ වචී කර්මයෙන් හා පිරිසිදු වූ මනෝ කර්මයෙන්ය. පින්වත් මහණෙනි, මේ කරුණු ....(පෙ).... ඒ අයුරින්ම සුගතියේ උපදිනවා.",
  "ai_short_intro": "කාය, වචී, මනෝ කර්මයන්හි පාරිශුද්ධතාවය අනුව සංසාර චර්මවල ප්‍රතිඵල විස්තර කිරීම",
  "ai_detailed_summary": "පුද්ගලයෙකුගේ මරණින් මතු උපත තීරණය කරන ප්‍රධාන සාධකයන් වන්නේ ඔහු විසින් සිදු කරනු ලබන කාය, වචී සහ මනෝ කර්මයන්හි ගුණයයි. කාය කර්මයෙන්, වචී කර්මයෙන් සහ මනෝ කර්මයෙන් අපිරිසිදු වූ පුද්ගලයෙකු අනිවාර්යයෙන්ම දුක්ඛිත වූ නිරය වැනි අපාය භවයන්හි උපත ලබයි.\n\nමීට ප්‍රතිවිරුද්ධව, කාය කර්මයෙන්, වචී කර්මයෙන් සහ මනෝ කර්මයෙන් පිරිසිදු වූ පුද්ගලයෙකු සුගතිලෝකයන්හි උපත ලබයි. මෙලෙස කර්මයේ පිරිසිදු බව සහ අපිරිසිදු බව මත පුද්ගලයෙකුගේ ගමනාන්තය තීරණය වන බව මෙහි අවධාරණය කෙරේ."
}