{
  "nikaya": "චතුක්ක නිපාතෝ",
  "vagga": "4.5.4.5. පඤ්චම කම්ම සුත්තං",
  "sutta_title": "4.5.4.5. කර්මය ගැන වදාළ පස්වෙනි දෙසුම",
  "description": "",
  "pali": "චත්තාරිමානි භික්ඛවේ කම්මානි මයා සයං අභිඤ්ඤා සච්ඡිකත්වා පවේදිතානි. කතමානි චත්තාරි? අත්ථි භික්ඛවේ කම්මං කණ්හං කණ්හවිපාකං. අත්ථි භික්ඛවේ කම්මං සුක්කං සුක්කවිපාකං. අත්ථි භික්ඛවේ කම්මං කණ්හසුක්කං කණ්හසුක්කවිපාකං. අත්ථි භික්ඛවේ කම්මං අකණ්හං අසුක්කං අකණ්හඅසුක්කවිපාකං කම්මක්ඛයාය සංවත්තති. කතමඤ්ච භික්ඛවේ කම්මං කණ්හං කණ්හවිපාකං? ඉධ භික්ඛවේ ඒකච්චේන මාතා ජීවිතා වෝරෝපිතා හෝති, පිතා ජීවිතා වෝරෝපිතෝ හෝති, අරහං ජීවිතා වෝරෝපිතෝ හෝති, තථාගතස්ස දුට්ඨේන චිත්තේන ලෝහිතං උප්පාදිතා හෝති. සංඝෝපි භින්නෝ හෝති. ඉදං වුච්චති භික්ඛවේ කම්මං කණ්හං කණ්හවිපාකං. කතමඤ්ච භික්ඛවේ කම්මං සුක්කං සුක්කවිපාකං? ඉධ භික්ඛවේ ඒකච්චෝ පාණාතිපාතා පටිවිරතෝ හෝති, අදින්නාදානා පටිවිරතෝ හෝති, කාමේසු මිච්ඡාචාරා පටිවිරතෝ හෝති, මුසාවාදා පටිවිරතෝ හෝති, පිසුණාවාචා පටිවිරතෝ හෝති, ඵරුසාවාචා පටිවිරතෝ හෝති, සම්ඵප්පලාපා පටිවිරතෝ හෝති, අනභිජ්ඣාලු‍ හෝති, අබ්‍යාපන්නචිත්තෝ හෝති, සම්මාදිට්ඨිකෝ හෝති. ඉදං වුච්චති භික්ඛවේ කම්මං සුක්කං සුක්කවිපාකං. කතමඤ්ච භික්ඛවේ කම්මං කණ්හසුක්කං කණ්හසුක්කවිපාකං? ඉධ භික්ඛවේ ඒකච්චෝ සබ්‍යාපජ්ඣම්පි අබ්‍යාපජ්ඣම්පි කායසංඛාරං අභිසංඛරෝති, ....(පෙ).... ඉදං වුච්චති භික්ඛවේ කම්මං කණ්හසුක්කං කණ්හසුක්කවිපාකං. කතමඤ්ච භික්ඛවේ කම්මං අකණ්හං අසුක්කං අකණ්හඅසුක්කවිපාකං කම්මක්ඛයාය සංවත්තති? තත්‍ර භික්ඛවේ යමිදං කම්මං කණ්හං කණ්හවිපාකං (තස්ස පහාණාය යා චේතනා) ....(පෙ).... ඉදං වුච්චති භික්ඛවේ කම්මං අකණ්හං අසුක්කං අකණ්හාසුක්කවිපාකං කම්මක්ඛයාය සංවත්තති. ඉමානි ඛෝ භික්ඛවේ චත්තාරි කම්මානි මයා සයං අභිඤ්ඤා සච්ඡිකත්වා පවේදිතානීති.",
  "sinhala": "මහණෙනි, මා විසින් මේ කර්ම සතර ස්වකීය විශිෂ්ට ඥානයෙන් සාක්ෂාත් කොට ප්‍රකාශ කරන ලද්දේ ය. ඒ කවර සතරක් ද යත්; මහණෙනි, අඳුරු විපාක ඇති අඳුරු කර්මයක් ඇත්තේ ය. මහණෙනි, දීප්තිමත් විපාක ඇති දීප්තිමත් කර්මයක් ඇත්තේ ය. මහණෙනි, අඳුරු වූ ත්, දීප්තිමත් වූ ත් විපාක ඇති අඳුරු වූ ත්, දීප්තිමත් වූ ත් කර්මයක් ඇත්තේ ය. මහණෙනි, කර්ම ක්ෂය වීම පිණිස පවතින්නා වූ අඳුරු ත් නොවන දීප්තිමත් නොවන විපාක ඇති අඳුරු ත් නොවන දීප්තිමත් නොවන කර්මයක් ඇත්තේ ය. 1. මහණෙනි, අඳුරු විපාක ඇති අඳුරු කර්මය යනු කුමක් ද? මහණෙනි, මෙහිලා ඇතැමෙක් තම මව් මරන්නේ වෙයි. තම පියා මරන්නේ වෙයි. රහතුන් මරන්නේ වෙයි. දුෂ්ට සිතින් තථාගතයන්ගේ සිරුරෙහි ලේ සොලවන්නේ වෙයි. සංඝභේදය කරන්නේ වෙයි. මහණෙනි, මෙය අඳුරු විපාක ඇති අඳුරු කර්මය යැයි කියනු ලැබේ. 2. මහණෙනි, දීප්තිමත් විපාක ඇති දීප්තිමත් කර්මය යනු කුමක් ද? මහණෙනි, මෙහිලා ඇතැමෙක් සතුන් මැරීමෙන් වැළකුණේ වෙයි. සොරකම් කිරීමෙන් වැළකුණේ වෙයි. වැරදි කාමසේවනයෙන් වැළකුණේ වෙයි. බොරු කීමෙන් වැළකුණේ වෙයි. කේළාම් කීමෙන් වැළකුණේ වෙයි. ඵරුෂ වචනයෙන් වැළකුණේ වෙයි. නිසරු බස් දෙඩීමෙන් වැළකුණේ වෙයි. අන් සතු දෙයට ලෝභ නොකරන්නේ වෙයි. කෝප රහිත සිත් ඇත්තේ වෙයි. සම්‍යක් දෘෂ්ටියෙන් යුක්ත වූයේ වෙයි. මහණෙනි, මෙය දීප්තිමත් විපාක ඇති දීප්තිමත් කර්මය යැයි කියනු ලැබේ. 3. මහණෙනි, අඳුරු වූ ත්, දීප්තිමත් වූ ත් විපාක ඇති අඳුරු වූ ත්, දීප්තිමත් වූ ත් කර්මය යනු කුමක් ද? මහණෙනි, ඇතැමෙක් දොස් සහිත වූ ත්, දොස් රහිත වූ ත් කාය සංස්කාර රැස් කරන්නේ වෙයි. ….(පෙ)…. (වචී සංස්කාර ….(පෙ)…. මනෝ සංස්කාර රැස් කරන්නේ වෙයි) මහණෙනි, මෙය අඳුරු වූ ත්, දීප්තිමත් වූ ත් විපාක ඇති අඳුරු වූ ත්, දීප්තිමත් වූ ත් කර්මය යැයි කියනු ලැබේ. 4. මහණෙනි, කර්මය ක්ෂය වීම පිණිස පවතින්නා වූ අඳුරු ත් නොවන දීප්තිමත් නොවන විපාක ඇති අඳුරු ත් නොවන දීප්තිමත් නොවන කර්මය යනු කුමක් ද? මහණෙනි, එහිලා යම් කර්මයක් අඳුරු වූ ත්, අඳුරු විපාක ඇත්තේ ත් වේ ද, ඒ කර්මය ප්‍රහාණය කිරීමට යම් චේතනාවක් ඇද්ද, ….(පෙ)…. මහණෙනි, කර්මය ක්ෂය වීම පිණිස පවතින්නා වූ අඳුරු ත් නොවන දීප්තිමත් නොවන විපාක ඇති අඳුරු ත් නොවන දීප්තිමත් නොවන කර්මය යැයි කියනු ලැබේ. මහණෙනි, මා විසින් මේ කර්ම සතර ස්වකීය විශිෂ්ට ඥානයෙන් සාක්ෂාත් කොට ප්‍රකාශ කරන ලද්දේ ය.",
  "ai_short_intro": "කර්ම විපාකවල ස්වභාවය සහ ඒවා ප්‍රහාණය කිරීමේ මාර්ගය පිළිබඳ විස්තරය"
}