{
  "nikaya": "පඤ්චක නිපාතෝ",
  "vagga": "5.2.5.1. පඨම සම්පදා සුත්තං",
  "sutta_title": "5.2.5.1. සම්පත්ති ගැන වදාළ පළමු දෙසුම",
  "description": "",
  "pali": "(සාවත්ථිනිදානං:) පඤ්චිමා භික්ඛවේ සම්පදා. කතමා පඤ්ච? සද්ධාසම්පදා සීලසම්පදා සුතසම්පදා චාගසම්පදා පඤ්ඤාසම්පදා. ඉමා ඛෝ භික්ඛවේ පඤ්ච සම්පදාති.",
  "sinhala": "සැවැත් නුවර දී ය ….. මහණෙනි, මේ සම්පත්තීහු පසකි. ඒ කවර පසක් ද යත්; ශ්‍රද්ධා සම්පත්තිය, සීල සම්පත්තිය, ශ්‍රැත සම්පත්තිය, ත්‍යාග සම්පත්තිය, ප්‍රඥා සම්පත්තිය ය. මහණෙනි, මේ වනාහී සම්පත්තීහු පස යි.",
  "ai_short_intro": "ශ්‍රද්ධාව, සීලය, ශ්‍රැතය, ත්‍යාගය සහ ප්‍රඥාව යන සම්පත් පදනම මත ජීවිතය ගොඩනැගීම"
}