{
  "nikaya": "පඤ්චක නිපාතෝ",
  "vagga": "5.4.5.2. ද්‍රෝණ සුත්තං",
  "sutta_title": "5.4.5.2. ද්‍රෝණ බමුණාට වදාළ දෙසුම",
  "description": "",
  "pali": "(සාවත්ථිනිදානං) අථ ඛෝ දෝණෝ බ්‍රාහ්මණෝ යේන භගවා තේනුපසංකමි. උපසංකමිත්වා භගවතා සද්ධිං සම්මෝදි. සම්මෝදනීයං කථං සාරාණීයං වීතිසාරෙත්වා ඒකමන්තං නිසීදි. ඒකමන්තං නිසින්නෝ ඛෝ දෝණෝ බ්‍රාහ්මණෝ භගවන්තං ඒතදවෝච: සුතං මේතං භෝ ගෝතම: “න සමණෝ ගෝතමෝ බ්‍රාහ්මණේ ජිණ්ණේ වුද්ධේ මහල්ලකේ අද්ධගතේ වයෝ අනුප්පත්තේ අභිවාදේති වා පච්චුට්ඨේති වා ආසනේන වා නිමන්තේතී”ති. තයිදං භෝ ගෝතම තථේව, න හි භවං ගෝතමෝ බ්‍රාහ්මණේ ජිණ්ණේ වුද්ධේ මහල්ලකේ අද්ධගතේ වයෝ අනුප්පත්තේ අභිවාදේති වා පච්චුට්ඨේති වා ආසනේන වා නිමන්තේතීති. තයිදං භෝ ගෝතම න සම්පන්නමේවාති. (භගවා:)\n“ත්වම්පි නෝ දෝණ, බ්‍රාහ්මණෝ පටිජානාසී?”ති. යං හි තං භෝ ගෝතම සම්මා වදමානෝ වදෙය්‍ය: “බ්‍රාහ්මණෝ උභතෝ සුජාතෝ මාතිතෝ ච පිතිතෝ ච, සංසුද්ධගහණිකෝ යාව සත්තමා පිතාමහයුගා, අක්ඛිත්තෝ අනුපක්කුට්ඨෝ ජාතිවාදේන, අජ්ඣායකෝ මන්තධරෝ, තිණ්ණං වේදානං පාරගූ සනිඝණ්ඩුකේටුභානං සාක්ඛරප්පභේදානං ඉතිහාසපඤ්චමානං, පදකෝ වෙය්‍යාකරණෝ, ලෝකායතමහාපුරිසලක්ඛණේසු අනවයෝ”ති මමේව තං භෝ ගෝතම සම්මා වදමානෝ වදෙය්‍ය. අහං හි භෝ ගෝතම බ්‍රාහ්මණෝ උභතෝ සුජාතෝ මාතිතෝ ච පිතිතෝ ච, සංසුද්ධගහණිකෝ යාව සත්තමා පිතාමහයුගා, අක්ඛිත්තෝ අනුපක්කුට්ඨෝ ජාතිවාදේන. අජ්ඣායකෝ මන්තධරෝ, තිණ්ණං වේදානං පාරගූ සනිඝණ්ඩුකේටුභානං සාක්ඛරප්පභේදානං ඉතිහාසපඤ්චමානං, පදකෝ වෙය්‍යාකරණෝ, ලෝකායත මහාපුරිසලක්ඛණේසු අනවයෝති. යේ ඛෝ තේ දෝණ, බ්‍රාහ්මණානං පුබ්බකා ඉසයෝ - මන්තානං කත්තාරෝ මන්තානං පවත්තාරෝ, යේසඤ්චිදං ඒතරහි බ්‍රාහ්මණා පෝරාණං මන්තපදං ගීතං පවුත්තං සමිහිතං තදනුගායන්ති, තදනුභාසන්ති, භාසිතමනුභාසන්ති, සජ්ඣායිතමනුසජ්ඣායන්ති, වාචිතමනුවාචෙන්ති, සෙය්‍යථීදං: අට්ටකෝ වාමකෝ වාමදේවෝ වෙස්සාමිත්තෝ යමතග්ගි අංගීරසෝ භාරද්වාජෝ වාසෙට්ඨෝ කස්සපෝ භගු. ත්‍යාස්සුමේ පඤ්ච බ්‍රාහ්මණේ පඤ්ඤාපෙන්ති: බ්‍රහ්මසමං, දේවසමං, මරියාදං, සම්භින්නමරියාදං, බ්‍රාහ්මණ චණ්ඩාලං යේව පඤ්චමං. තේසං ත්වං දෝණ කතමෝ?ති. න ඛෝ මයං භෝ ගෝතම, ඉමේ පඤ්ච බ්‍රාහ්මණේ ජානාම. අථ ඛෝ මයං බ්‍රාහ්මණාත්වේව ජානාම. සාධු මේ භවං ගෝතමෝ තථා ධම්මං දේසේතු යථා අහං ඉමේ පඤ්ච බ්‍රාහ්මණේ ජානෙය්‍යන්ති. තේන හි බ්‍රාහ්මණ සුණෝහි, සාධුකං මනසිකරෝහි, භාසිස්සාමීති. ඒවං හෝති ඛෝ දෝණෝ බ්‍රාහ්මණෝ භගවතෝ පච්චස්සෝසි. භගවා ඒතදවෝච: කථඤ්ච දෝණ, බ්‍රාහ්මණෝ බ්‍රහ්මසමෝ හෝති? ඉධ දෝණ බ්‍රාහ්මණෝ උභතෝ සුජාතෝ හෝති මාතිතෝ ච පිතිතෝ ච, සංසුද්ධගහණිකෝ යාව සත්තමා පිතාමහයුගා, අක්ඛිත්තෝ අනුපක්කුට්ඨෝ ජාතිවාදේන. සෝ අට්ඨචත්තාළීස වස්සානි කෝමාරබ්‍රහ්මචරියං චරති මන්තේ අධීයමානෝ අට්ඨචත්තාළීස වස්සානි කෝමාරබ්‍රහ්මචරියං චරිත්වා මන්තේ අධීයිත්වා ආචරියස්ස ආචරියධනං පරියේසති ධම්මේනේව, නෝ අධම්මේන. තත්ථ ච දෝණ කෝ ධම්මෝ? නේව කසියා, න වණිජ්ජාය, න ගෝරක්ඛේන, න ඉස්සත්ථේන න රාජපෝරිසේන න සිප්පඤ්ඤතරේන, කේවලං භික්ඛාචරියාය කපාලං අනතිමඤ්ඤමානෝ. සෝ ආචරියස්ස ආචරිය ධනං නිය්‍යාදෙත්වා කේසමස්සුං ඕහාරෙත්වා කාසායානි වත්ථානි අච්ඡාදෙත්වා අගාරස්මා අනගාරියං පබ්බජති. සෝ ඒවං පබ්බජිතෝ සමානෝ මෙත්තාසහගතේන චේතසා ඒකං දිසං ඵරිත්වා විහරති. තථා දුතියං - තථා තතියං - තථා චතුත්ථිං - ඉති උද්ධමධෝ තිරියං සබ්බධී සබ්බත්තතාය2 සබ්බාවන්තං ලෝකං මෙත්තාසහගතේන චේතසා විපුලේන මහග්ගතේන අප්පමාණේන අවේරේන අව්‍යාපජ්ඣනේ ඵරිත්වා විහරති. කරුණා ....(පෙ).... මුදිතා ....(පෙ).... උපෙක්ඛාසහගතේන චේතසා ඒකං දිසං ඵරිත්වා විහරති. තථා දුතියං - තථා තතියං - තථා චතුත්ථිං - ඉති උද්ධමධෝ තිරියං සබ්බධී සබ්බත්තතාය2 සබ්බාවන්තං ලෝකං උපෙක්ඛාසහගතේන චේතසා විපුලේන මහග්ගතේන අප්පමාණේන අවේරේන අව්‍යාපජ්ඣනේ ඵරිත්වා විහරති. සෝ ඉමේ චත්තාරෝ බ්‍රහ්මවිහාරේ භාවෙත්වා කායස්ස භේදා පරම්මරණා සුගතිං බ්‍රහ්මලෝකං උප්පජ්ජති. ඒවං ඛෝ දෝණ බ්‍රාහ්මණෝ බ්‍රහ්මසමෝ හෝති. කතඤ්ච දෝණ බ්‍රාහ්මණෝ දේවසමෝ හෝති? ඉධ දෝණ බ්‍රාහ්මණෝ උභතෝ සුජාතෝ හෝති මාතිතෝ ච පිතිතෝ ච, සංසුද්ධගහණිකෝ යාව සත්තමා පිතාමහයුගා, අක්ඛිත්තෝ අනුපක්කුට්ඨෝ ජාතිවාදේන. සෝ අට්ඨචත්තාළීස වස්සානි කෝමාරං බ්‍රහ්මචරියං චරති මන්තේ අධීයමානෝ. අට්ඨචත්තාළීස වස්සානි කෝමාරබ්‍රහ්මචරියං චරිත්වා මන්තේ අධීයිත්වා ආචරියස්ස ආචරියධනං පරියේසති ධම්මේනේව නෝ අධම්මේන. තත්ථ ච දෝණ කෝ ධම්මෝ? නේව කසියා, න වණිජ්ජාය, න ගෝරක්ඛේන, න ඉස්සත්ථේන, න රාජපෝරිසේන, න සිප්පඤ්ඤතරේන, කේවලං භික්ඛාචරියාය කපාලං අනතිමඤ්ඤමානෝ. සෝ ආචරියස්ස ආචරියධනං නීයාදෙත්වා දාරං පරියේසති ධම්මේනේව නෝ අධම්මේන. තත්ථ ච දෝණ කෝ ධම්මෝ? නේව කයේන, න වික්කයේන, බ්‍රාහ්මණිං යේව උදකූපස්සට්ඨං. සෝ බ්‍රාහ්මණිං යේව ගච්ඡති. න ඛත්තියිං. න වෙස්සිං, න සුද්දිං, න චණ්ඩාලිං, න නේසාදිං, න වේණිං, න රථකාරිං, න පුක්කුසිං ගච්ඡති. න ගබ්භිනිං ගච්ඡති, න පායමානං ගච්ඡති, න අනුතුනිං ගච්ඡති. කස්මා ච දෝණ බ්‍රාහ්මණෝ න ගබ්භිනිං ගච්ඡති: සචේ දෝණ බ්‍රාහ්මණෝ ගබ්භිනිං ගච්ඡති, අතිමීළ්හජෝ නාම සෝ හෝති මාණවකෝ වා මාණවිකා වා. තස්මා දෝණ බ්‍රාහ්මණෝ න ගබ්භිනිං ගච්ඡති. කස්මා ච දෝණ බ්‍රාහ්මණෝ න පායමානං ගච්ඡති: සචේ දෝණ බ්‍රාහ්මණෝ පායමානං ගච්ඡති, අසුචි පටිපීතෝ නාම සෝ හෝති මාණවකෝ වා මාණවිකා වා. තස්මා දෝණ බ්‍රාහ්මණෝ න පායමානං ගච්ඡති. කස්මා ච දෝණ බ්‍රාහ්මණෝ න අනුතුනිං ගච්ඡති: සචේ දෝණ බ්‍රාහ්මණෝ අනුතුනිං ගච්ඡති තස්ස සා හෝති බ්‍රාහ්මණී නේව කාමත්ථා න දවත්ථා න රතත්ථා, පජත්ථාව බ්‍රාහ්මණස්ස බ්‍රාහ්මණී හෝති. සෝ මිථුනං උප්පාදෙත්වා කේසමස්සුං ඕහාරෙත්වා කාසායානි වත්ථානි අච්ඡාදෙත්වා අගාරස්මා අනගාරියං පබ්බජති. සෝ ඒවං පබ්බජිතෝ සමානෝ විවිච්චේව කාමේහි චතුත්ථං ඣානං උපසම්පජ්ජ විහරති. සෝ ඉමේ චත්තාරෝ ඣානේ භාවෙත්වා කායස්ස භේදා පරම්මරණා සුගතිං සග්ගං ලෝකං උපපජ්ජති. ඒවං ඛෝ දෝණ බ්‍රාහ්මණෝ දේවසමෝ හෝති. කථඤ්ච දෝණ, බ්‍රාහ්මණෝ මරියාදෝ හෝති? ඉධ දෝණ බ්‍රාහ්මණෝ උභතෝ සුජාතෝ හෝති මාතිතෝ ච පිතිතෝ ච, සංසුද්ධගහණිකෝ යාව සත්තමා පිතාමහයුගා, අක්ඛිත්තෝ අනුපක්කුට්ඨෝ ජාතිවාදේන. සෝ අට්ඨචත්තාළීසවස්සානි කෝමාරං බ්‍රහ්මචරියං චරති මන්තේ අධීයමානෝ. අට්ඨචත්තාළීස වස්සානි කෝමාරං බ්‍රහ්මචරියං චරිත්වා මන්තේ අධීයිත්වා ආචරියස්ස ආචරියධනං පරියේසති ධම්මේනේව නෝ අධම්මේන. තත්ථ ච දෝණ කෝ ධම්මෝ? නේව කසියා, න වණිජ්ජාය, න ගෝරක්ඛේන, න ඉස්සත්ථේන, න රාජපෝරිසේන, න සිප්පඤ්ඤතරේන, කේවලං භික්ඛාචරියාය කපාලං අනතිමඤ්ඤමානෝ. සෝ ආචරියස්ස ආචරියධනං නීයාදෙත්වා දාරං පරියේසති ධම්මේනේව නෝ අධම්මේන. තත්ථ ච දෝණ කෝ ධම්මෝ? නේව කයේන, න වික්කයේන, බ්‍රාහ්මණිං යේව උදකූපස්සට්ඨං. සෝ බ්‍රාහ්මණිං යේව ගච්ඡති, න ඛත්තියිං, න වෙස්සිං, න සුද්දිං, න චණ්ඩාලිං, න නේසාදිං, න වේණිං, න රථකාරිං, න පුක්කුසිං ගච්ඡති. න ගබ්භිනිං ගච්ඡති. න පායමානං ගච්ඡති න අනුතුනිං ගච්ඡති. කස්මා ච දෝණ බ්‍රාහ්මණෝ න ගබ්භිනිං ගච්ඡති? සචේ දෝණ බ්‍රාහ්මණෝ ගබ්භිනිං ගච්ඡති ....(පෙ).... පජත්ථා ව බ්‍රාහ්මණස්ස බ්‍රාහ්මණී හෝති. සෝ මිථුනං උප්පාදෙත්වා තමේව පුත්තස්සාදං නිකාමයමානෝ කුටුම්බං අජ්ඣාවසති, න අගාරස්මා අනගාරියං පබ්බජති. යාව පෝරාණානං බ්‍රාහ්මණානං මරියාදා, තත්ථ තිට්ඨති, තං න වීතික්කමති ‘යාව පෝරාණානං බ්‍රාහ්මණානං මරියාදෝ තත්ථ බ්‍රාහ්මණෝ ඨිතෝ තං න වීතික්කමතී’ති ඛෝ දෝණ තස්මා “බ්‍රාහ්මණෝ මරියාදෝ” ති වුච්චති. ඒවං ඛෝ දෝණ බ්‍රාහ්මණෝ මරියාදෝ හෝති. කථඤ්ච දෝණ, බ්‍රාහ්මණෝ සම්භින්නමරියාදෝ හෝති? ඉධ දෝණ බ්‍රාහ්මණෝ උභතෝ සුජාතෝ හෝති ....(පෙ).... අනුපක්කුට්ඨෝ ජාතිවාදේන. සෝ අට්ඨචත්තාළීස වස්සානි කෝමාරං බ්‍රහ්මචරියං චරති මන්තේ අධීයමානෝ. අට්ඨචත්තාළීස වස්සානි කෝමාරං බ්‍රහ්මචරියං චරිත්වා මන්තේ අධීයිත්වා ආචරියස්ස ආචරියධනං පරියේසති, ධම්මේනේව නෝ අධම්මේන. තත්ථ ච දෝණ කෝ ධම්මෝ? නේව කසියා න වණිජ්ජාය න ගෝරක්ඛේන න ඉස්සත්ථේන, න රාජපෝරිසේන, න සිප්පඤ්ඤතරේන, කේවලං භික්ඛාචරියාය කපාලං අනතිමඤ්ඤමානෝ. සෝ ආචරියස්ස ආචරියධනං නීයාදෙත්වා දාරං පරියේසති ධම්මේන’පි අධම්මේන’පි. කයේන’පි වික්කයේන’පි බ්‍රාහ්මණිම්පි උදකූපස්සට්ඨං. සෝ බ්‍රාහ්මණිම්පි ගච්ඡති, ඛත්තියිම්පි ගච්ඡති, වෙස්සිම්පි ගච්ඡති, සුද්දිම්පි ගච්ඡති, චණ්ඩාලිම්පි ගච්ඡති, නේසාදිම්පි ගච්ඡති, වේණිම්පි ගච්ඡති, රථකාරිම්පි ගච්ඡති, පුක්කුසිම්පි ගච්ඡති, ගභිනිම්පි ගච්ඡති, පායමානම්පි ගච්ඡති, උතුනිම්පි ගච්ඡති, අනුතුනිම්පි ගච්ඡති, තස්ස සා හෝති බ්‍රාහ්මණී කාමත්ථාපි දවත්ථාපි රතත්ථාපි. න පජත්ථාව බ්‍රාහ්මණස්ස බ්‍රාහ්මණී හෝති. යාව පෝරාණානං බ්‍රාහ්මණානං මරියාදා, තත්ථ න තිට්ඨති, තං වීතික්කමති. ‘යාව පෝරාණානං බ්‍රාහ්මණානං මරියාදා තත්ථ බ්‍රාහ්මණෝ න ඨිතෝ, තං වීතික්කමතී’ති ඛෝ දෝණ තස්මා “බ්‍රාහ්මණෝ සම්භින්නමරියාදෝ” ති වුච්චති. ඒවං ඛෝ දෝණ බ්‍රාහ්මණෝ සම්භින්නමරියාදෝ හෝති. කථඤ්ච දෝණ, බ්‍රාහ්මණෝ බ්‍රාහ්මණ චණ්ඩාලෝ හෝති? ඉධ දෝණ බ්‍රාහ්මණෝ උභතෝ සුජාතෝ හෝති මාතිතෝ ච පිතිතෝ ච, සංසුද්ධගහණිකෝ යාව සත්තමා පිතාමහයුගා, අක්ඛිත්තෝ අනුපක්කුට්ඨෝ ජාතිවාදේන. සෝ අට්ඨචත්තාළීස වස්සානි කෝමාරං බ්‍රහ්මචරියං චරති මන්තේ අධීයමානෝ. අට්ඨචත්තාළීස වස්සානි කෝමාරං බ්‍රහ්මචරියං චරිත්වා මන්තේ අධීයිත්වා ආචරියස්ස ආචරියධනං පරියේසති ධම්මේන’පි අධම්මේන’පි කසියා’පි වණිජ්ජාය’පි ගෝරක්ඛේන’පි ඉස්සත්ථේන’පි රාජපෝරිසේන’පි සිප්පඤ්ඤතරේන’පි කේවලම්පි භික්ඛාචරියාය කපාලං අනතිමඤ්ඤමානෝ. සෝ ආචරියස්ස ආචරියධනං නීයාදෙත්වා දාරං පරියේසති ධම්මේන’පි අධම්මේන’පි කයේන’පි වික්කයේන’පි උදකූපස්සට්ඨං. සෝ බ්‍රාහ්මණිම්පි ගච්ඡති, ඛත්තියිම්පි ගච්ඡති, වෙස්සිම්පි ගච්ඡති, සුද්දිම්පි ගච්ඡති, චණ්ඩාලිම්පි ගච්ඡති, නේසාදිම්පි ගච්ඡති, වේණිම්පි ගච්ඡති රථකාරිම්පි ගච්ඡති, පුක්කුසිම්පි ගච්ඡති, ගබ්භිනිම්පි ගච්ඡති, පායමානම්පි ගච්ඡති, උතුනිම්පි ගච්ඡති, අනුතුනිම්පි ගච්ඡති තස්ස සා හෝති බ්‍රාහ්මණී කාමත්ථාපි දවත්ථාපි රතත්ථාපි, න පජත්ථාව බ්‍රාහ්මණස්ස බ්‍රාහ්මණී හෝති. සෝ සබ්බකම්මේහි ජීවිකං කප්පේති, කමේනං බ්‍රාහ්මණා ඒවමාහංසු: “කස්මා භවං බ්‍රාහ්මණෝ පටිජානමානෝ සබ්බකම්මේහි ජීවිකං කප්පේති?”ති. සෝ ඒවමාහ: “සෙය්‍යථාපි භෝ අග්ගි සුචිම්පි දහති, අසුචිම්පි දහති න ච තේන අග්ගි උපලිප්පති, ඒවමේව ඛෝ භෝ සබ්බකම්මේහි චේපි බ්‍රාහ්මණෝ ජීවිකං කප්පේති, න ච තේන බ්‍රාහ්මණෝ උපලිප්පති”. සබ්බකම්මේහි ජීවිකංකප්පේතීති ඛෝ දෝණ තස්මා බ්‍රාහ්මණෝ “බ්‍රාහ්මණ චණ්ඩාලෝ”ති වුච්චති. ඒවං ඛෝ දෝණ බ්‍රාහ්මණෝ බ්‍රාහ්මණචණ්ඩාලෝ හෝති. යේ ඛෝ දෝණ බ්‍රාහ්මණානං පුබ්බකා ඉසයෝ - මන්තානං කත්තාරෝ මන්තානං පවත්තාරෝ, යේස්‍යඤ්චිදං ඒතරහි බ්‍රාහ්මණා පෝරාණං මන්තපදං ගීතං පවුත්තං සමිහිතං තදනුගායන්ති, තදනුභාසන්ති, භාසිතමනුභාසන්ති, සජ්ඣායිතමනුසජ්ඣායන්ති, වාචිතමනුවාචෙන්ති, සෙය්‍යථීදං: අට්ටකෝ වාමකෝ වාමදේවෝ වෙස්සාමිත්තෝ යමතග්ගි අංගීරසෝ භාරද්වාජෝ වාසෙට්ඨෝ කස්සපෝ භගු. ත්‍යාස්සුමේ පඤ්ච බ්‍රාහ්මණේ පඤ්ඤාපෙන්ති: බ්‍රහ්මසමං, දේවසමං, මරියාදං, සම්හින්නමරියාදං, බ්‍රාහ්මණචණ්ඩාලංයේව පඤ්චමං. තේසං ත්වං දෝණ කතමෝ?ති. ඒවං සන්තේ මයං භෝ ගෝතම බ්‍රාහ්මණචණ්ඩාලම්පි න පුරේම. අභික්කන්තං භෝ ගෝතම ....(පෙ).... උපාසකං මං භවං ගෝතමෝ ධාරේතු අජ්ජතග්ගේ පාණුපේතං සරණං ගතන්ති.",
  "sinhala": "සැවැත් නුවර දී ය ….. එකල්හී ද්‍රෝණ බ්‍රාහ්මණයා භාග්‍යවතුන් වහන්සේ යම් තැනක වැඩසිටි සේක් ද, එතැනට පැමිණියේ ය. පැමිණ භාග්‍යවතුන් වහන්සේ සමඟ සතුටු වූයේ ය. සතුටු විය යුතු පිළිසඳර කතා බහ නිමවා එකත්පස් ව හිඳ ගත්තේ ය. එකත්පස් ව හුන් ද්‍රෝණ බමුණා භාග්‍යවතුන් වහන්සේට මෙය පැවසුවේය. “භවත් ගෞතමයන් වහන්ස, මෙකරුණ මවිසින් අසන ලද්දේ ය. එනම් ‘ශ්‍රමණ භවත් ගෞතම තෙමේ ජරා ජීර්ණ වූ, වයෝවෘද්ධ වූ, මහළු වූ, පිළිවෙළින් වයසට ගිය, බ්‍රාහ්මණයන්ට නොවඳින්නේ හෝ වෙයි. දැක හුනස්නෙන් නොනැගිටින්නේ හෝ වෙයි. අසුනින් නොපවරන්නේ හෝ වෙයි’ කියා ය. භවත් ගෞතමයෙනි, එය එසේ ම ය. ශ්‍රමණ භවත් ගෞතම තෙමේ ජරා ජීර්ණ වූ, වයෝවෘද්ධ වූ, මහළු වූ, පිළිවෙළින් වයසට ගිය, බ්‍රාහ්මණයන්ට නොවඳින්නේ හෝ වෙයි. දැක හුනස්නෙන් නොනැගිටින්නේ හෝ වෙයි. අසුනින් නොපවරන්නේ හෝ වෙයි. භවත් ගෞතමයන් වහන්ස, මෙය ගැලපෙන දෙයක් නම් නොවෙයි.” “ද්‍රෝණයෙනි, ඔබ ත් බ්‍රාහ්මණයෙක් වශයෙන් ප්‍රතිඥා දෙන්නෙහි ද?” “භවත් ගෞතමයන් වහන්ස, යමෙක් යම් කෙනෙකු අරභයා ‘මව් පසිනුත් පිය පසිනුත් යන දෙපසින් ම සුජාත උපතක් ලද, පිරිසිදු මව් කුසක් ඇති, සත්වෙනි මීමුතු පරපුර තෙක් ජාතිවාදයෙන් නින්දා නොලද, නොබැහැර කළ බ්‍රාහ්මණයා ය, උගන්වන්නා වූ වේද මන්ත්‍රධර වූ නිඝණ්ඩු, කේටූභ, සාක්ෂර ප්‍රභේද සහිත වූ ඉතිහාසය පස්වෙනි කොට ඇති ත්‍රිවේදයෙහි කෙළ පැමිණියේ ය, වේද පද හදාරණ, ව්‍යාකරණ දත්, ලෝකායත ශාස්ත්‍රයෙහි ද, මහා පුරුෂ ලක්ෂණයෙහි ද මනා දැනුමක් ඇති බ්‍රාහ්මණයා ය’ කියා මනාකොට කියන්නේ නම් භවත් ගෞතමයන් වහන්ස, ඒ මා සඳහා ම කියන්නේ ය. භවත් ගෞතමයන් වහන්ස, මම් වනාහී මව් පසිනුත් පිය පසිනුත් යන දෙපසින් ම සුජාත උපතක් ලද, පිරිසිදු මව් කුසක් ඇති, සත්වෙනි මීමුතු පරපුර තෙක් ජාතිවාදයෙන් නින්දා නොලද, නොබැහැර කළ අයෙක්මි. උගන්වන්නා වූ වේද මන්ත්‍රධර වූ නිඝණ්ඩු, කේටූභ, සාක්ෂර ප්‍රභේද සහිත වූ ඉතිහාසය පස්වෙනි කොට ඇති ත්‍රිවේදයෙහි කෙළ පැමිණියේ ය, වේද පද හදාරණ, ව්‍යාකරණ දත්, ලෝකායත ශාස්ත්‍රයෙහි ද, මහා පුරුෂ ලක්ෂණයෙහි ද මනා දැනුමක් ඇති බ්‍රාහ්මණයෙක් වෙමි.” “ද්‍රෝණය, බ්‍රාහ්මණයන්ගේ මන්ත්‍ර රචනා කළ, මන්ත්‍ර පැවසූ, පෙර සිටි ඍෂිවරු වෙත් ද, ඒ ඍෂිවරුන් විසින් ගයන ලද, කියන ලද, රැස් කරන ලද, ඒ පැරණි මන්ත්‍ර පද මෙකල බ්‍රාහ්මණවරු ඒ අනුව ගයත් නම්, ඒ අනුව කියත් නම්, ඒ අනුව හදාරවත් නම්, ඒ අනුව සජ්ඣායනා කරවත් නම්, ඒ අනුව වනපොත් කරවත් නම්, ඒ කවර ඍෂිවරුගේ ද? අට්ටක, වාමක, වාමදේව, වෙස්සාමිත්ත, යමතග්ගී, අංගීරස, භාරද්වාජ, වාසෙට්ඨ, කස්සප, භගු යන මේ දස ඍෂීහු ය. ඔවුහු පස් වැදෑරුම් බමුණන් පණවති. බ්‍රහ්මසම බමුණා ය, දේවසම බමුණා ය, සීමාව තුළ සිටින බමුණා ය, සීමා බිඳගත් බමුණා ය, පස්වෙනි සැඩොල් බමුණා ය වශයෙනි. ද්‍රෝණය, මොවුන් අතුරින් ඔබ අයත් වන්නේ කාට ද?” “භවත් ගෞතමයන් වහන්ස, අපි මේ පස් වැදෑරුම් බ්‍රාහ්මණයන් ගැන නොදනිමු. වැලිදු අපි බ්‍රාහ්මණයන් බව නම් දනිමු. භවත් ගෞතමයන් වහන්සේ යම් අයුරකින් මේ පංච බ්‍රාහ්මණයන් ගැන මම දැනගන්නෙම් ද, ඒ අයුරින් මට දහම් දෙසන සේක් නම් මැනැවි.” “එසේ වී නම් බ්‍රාහ්මණය, අසව. මැනැවින් මෙනෙහි කරව. පවසන්නෙමි.” “එසේ ය භවතැ”යි ද්‍රෝණ බ්‍රාහ්මණයා භාග්‍යවතුන් වහන්සේට පිළිතුරු දුන්නේ ය. භාග්‍යවතුන් වහන්සේ මෙය වදාළ සේක. “ද්‍රෝණය, බ්‍රාහ්මණයෙක් බ්‍රහ්මයා හා සමාන වන්නේ කෙසේ ද? ද්‍රෝණය, මෙහිලා බ්‍රාහ්මණ තෙමේ මව් පසිනුත් පිය පසිනුත් යන දෙපසින් ම සුජාත උපතක් ලද, පිරිසිදු මව් කුසක් ඇති, සත්වෙනි මීමුතු පරපුර තෙක් ජාතිවාදයෙන් නින්දා නොලද, බැහැර නොකළේ වෙයි. හේ සතලිස් අට වර්ෂයක් වේදමන්ත්‍ර හදාරමින් කුමර බඹසර හැසිරෙයි. සතලිස් අට වර්ෂයක් වේදමන්ත්‍ර හදාරමින් කුමර බඹසර හැසිරී ආචාර්යවරයාට ධර්මයෙන් ම ගුරුපඬුරු සොයයි. අධර්මයෙන් නොවෙයි. ද්‍රෝණය, එහිලා ධර්මය යනු කුමක් ද? ගොවිතැනෙනුත් නොවෙයි. වෙළඳාමෙනුත් නොවෙයි. ගවයන් රැකීමෙනුත් නොවෙයි. ධනුශ්ශිල්පයෙනුත් නොවෙයි. රාජපුරුෂ බවෙනුත් නොවෙයි. වෙනත් ශිල්පයකිනුත් නොවෙයි. හුදෙක් ම භික්ෂාවෙහි හැසිරීමෙන් අතට ගත් කබලට අවමන් නොකරමින් වෙසෙයි. හේ ආචාර්යවරයාට ගුරුපඬුරු සොයා දී කෙස් රැවුල් බහා කසාවත් හැඳ පොරොවා අනගාරික ව පැවිදි වෙයි. හේ එසේ පැවිදි වූයේ මෛත්‍රී සහගත සිතින් එක් දිශාවක් පතුරුවා වාසය කරයි. එසේ දෙවෙනි දිශාව ද, තුන්වෙනි දිශාව ද, සතරවෙනි දිශාව ද, උඩ යට සරස හැම තැන්හි සියළු දෙනාට සම ලෙසින් සියළු ලෝකයා හට මෛත්‍රී සහගත වූ මහත් වූ මහග්ගත වූ අප්‍රමාණ වූ අවෛරී වූ අව්‍යාපාද සිත පතුරුවා වාසය කරයි. කරුණා ….(පෙ)…. මුදිතා ….(පෙ)…. උපේක්ෂා සහගත සිතින් එක් දිශාවක් පතුරුවා වාසය කරයි. එසේ දෙවෙනි දිශාව ද, තුන්වෙනි දිශාව ද, සතරවෙනි දිශාව ද, උඩ යට සරස හැම තැන්හි සියළු දෙනාට සම ලෙසින් සියළු ලෝකයා හට උපේක්ෂා සහගත වූ මහත් වූ මහග්ගත වූ අප්‍රමාණ වූ අවෛරී වූ අව්‍යාපාද සිත පතුරවා වාසය කරයි. හේ මේ සතර බ්‍රහ්ම විහාරයන් වඩා කය බිඳී මරණින් මතු සුගති සංඛ්‍යාත බඹලොවෙහි ඉපදෙයි. මෙසේ ද්‍රෝණය, බ්‍රාහ්මණයා බ්‍රහ්මසම වෙයි. ද්‍රෝණය, බ්‍රාහ්මණයෙක් දෙවියන් හා සමාන වන්නේ කෙසේ ද? ද්‍රෝණය, මෙහිලා බ්‍රාහ්මණ තෙමේ මව් පසිනුත් පිය පසිනුත් යන දෙපසින් ම සුජාත උපතක් ලද, පිරිසිදු මව් කුසක් ඇති, සත්වෙනි මීමුතු පරපුර තෙක් ජාතිවාදයෙන් නින්දා නොලද, බැහැර නොකළේ වෙයි. හේ සතලිස් අට වර්ෂයක් වේදමන්ත්‍ර හදාරමින් කුමර බඹසර හැසිරෙයි. සතලිස් අට වර්ෂයක් වේදමන්ත්‍ර හදාරමින් කුමර බඹසර හැසිරී ආචාර්යවරයාට ධර්මයෙන් ම ගුරුපඬුරු සොයයි. අධර්මයෙන් නොවෙයි. ද්‍රෝණය, එහිලා ධර්මය යනු කුමක් ද? ගොවිතැනෙනුත් නොවෙයි. වෙළඳාමෙනුත් නොවෙයි. ගවයන් රැකීමෙනුත් නොවෙයි. ධනුශ්ශිල්පයෙනුත් නොවෙයි. රාජපුරුෂ බවෙනුත් නොවෙයි. වෙනත් ශිල්පයකිනුත් නොවෙයි. හුදෙක් ම භික්ෂාවෙහි හැසිරීමෙන් අතට ගත් කබලට අවමන් නොකරමින් වෙසෙයි. හේ ආචාර්යවරයාට ගුරුපඬුරු සොයා දී ධර්මයෙන් ම බිරිඳක් සොයයි. අධර්මයෙන් නොවෙයි. එහිලා ද්‍රෝණය, ධර්මය යනු කුමක් ද? මිලට ගන්නේ නොවෙයි, විකුණන්නේ නොවෙයි. අතපැන් වත්කොට දෙන බැමිණියක් ම සොයයි. හේ බැමිණිය ළඟට පමණක් යයි. ක්ෂත්‍රීය ගැහැණිය වෙත නොයයි. වෛශ්‍ය ගැහැණිය වෙත නොයයි. ශුද්‍ර ගැහැණිය වෙත නොයයි. සැඩොල් ගැහැණිය වෙත නොයයි. වැදි ගැහැණිය වෙත නොයයි. කුළුපොතු ගැහැණිය වෙත නොයයි. රථකාර ගැහැණිය වෙත නොයයි. පුක්කුස ගැහැණිය වෙත නොයයි. ගැබ්ගත් ගැහැණිය වෙත නොයයි. දරුවාට කිරි දෙන ගැහැණිය වෙත නොයයි. වැඩිවිය නොපත් ගැහැණිය වෙත නොයයි. ද්‍රෝණය, බ්‍රාහ්මණයා මක් නිසා ද ගැබිණිය වෙත නොයන්නේ ? ඉදින් ද්‍රෝණය, බ්‍රාහ්මණයා ගැබිණිය වෙත යයි නම්, ඒ දරුවා හෝ දැරිය මහා අසුචි රාශියෙහි උපදින්නේ වෙයි. එහෙයින් ද්‍රෝණය, බ්‍රාහ්මණයා ගැබිණිය කරා නොයයි. ද්‍රෝණය, බ්‍රාහ්මණයා මක් නිසා ද කිරිපොවන්නිය වෙත නොයන්නේ ? ඉදින් ද්‍රෝණය, බ්‍රාහ්මණයා දරුවාට කිරිපොවන්නිය වෙත යයි නම්, ඒ දරුවා හෝ දැරිය අසුචි පානය කරන්නේ වෙයි. එහෙයින් ද්‍රෝණය, බ්‍රාහ්මණයා කිරිපොවන්නිය කරා නොයයි. ද්‍රෝණය, බ්‍රාහ්මණයා මක් නිසා ද වැඩිවිය නොපත් ස්ත්‍රිය වෙත නොයන්නේ ? ඉදින් ද්‍රෝණය, බ්‍රාහ්මණයා වැඩිවිය නොපත් ස්ත්‍රිය වෙත යයි නම්, එය නොගැලපෙයි. බ්‍රාහ්මණයා හට බැමිණිය කාමයෙහි අරුත නොසපයන්නී වෙයි. ජවයෙහි අරුත නොසපයන්නී වෙයි. රතියෙහි අරුත නොසපයන්නී වෙයි. බ්‍රාහ්මණයා හට බැමිණිය දරු පරපුර බිහි කිරීම පිණිස ම වෙයි. හේ දරුවෙකු හෝ දැරියක උපදවා කෙස් රැවුල් බහා කසාවත් හැඳ පොරොවා ගෙන අනගාරික ව පැවිදි වෙයි. හේ එසේ පැවිදි වූයේ කාමයන්ගෙන් වෙන් ව ….(පෙ)…. සතරවෙනි ධ්‍යානයට සමවැදී වාසය කරන්නේ වෙයි. හේ මේ දැහැන් සතර වඩා කය බිඳී මරණින් මතු සුගති සංඛ්‍යාත ස්වර්ග ලෝකයෙහි ඉපදෙයි. මෙසේ ද්‍රෝණය, බ්‍රාහ්මණයා දේවසම වෙයි. ද්‍රෝණය, බ්‍රාහ්මණයෙක් තම සීමාවෙහි සිටින්නේ කෙසේ ද? ද්‍රෝණය, මෙහිලා බ්‍රාහ්මණ තෙමේ මව් පසිනුත් පිය පසිනුත් යන දෙපසින් ම සුජාත උපතක් ලද, පිරිසිදු මව් කුසක් ඇති, සත්වෙනි මීමුතු පරපුර තෙක් ජාතිවාදයෙන් නින්දා නොලද, බැහැර නොකළේ වෙයි. හේ සතලිස් අට වර්ෂයක් වේදමන්ත්‍ර හදාරමින් කුමර බඹසර හැසිරෙයි. සතලිස් අට වර්ෂයක් වේදමන්ත්‍ර හදාරමින් කුමර බඹසර හැසිරී ආචාර්යවරයාට ධර්මයෙන් ම ගුරුපඬුරු සොයයි. අධර්මයෙන් නොවෙයි. ද්‍රෝණය, එහිලා ධර්මය යනු කුමක් ද? ගොවිතැනෙනුත් නොවෙයි. වෙළඳාමෙනුත් නොවෙයි. ගවයන් රැකීමෙනුත් නොවෙයි. ධනුශ්ශිල්පයෙනුත් නොවෙයි. රාජපුරුෂ බවෙනුත් නොවෙයි. වෙනත් ශිල්පයකිනුත් නොවෙයි. හුදෙක් ම භික්ෂාවෙහි හැසිරීමෙන් අතට ගත් කබලට අවමන් නොකරමින් වෙසෙයි. හේ ආචාර්යවරයාට ගුරුපඬුරු සොයා දී ධර්මයෙන් ම බිරිඳක් සොයයි. අධර්මයෙන් නොවෙයි. එහිලා ද්‍රෝණය, ධර්මය යනු කුමක් ද? මිලට ගන්නේ නොවෙයි, විකුණන්නේ නොවෙයි. අතපැන් වත්කොට දෙන බැමිණියක් ම සොයයි. හේ බැමිණිය ළඟට පමණක් යයි. ක්ෂත්‍රීය ගැහැණිය වෙත නොයයි. වෛශ්‍ය ගැහැණිය වෙත නොයයි. ශුද්‍ර ගැහැණිය වෙත නොයයි. සැඩොල් ගැහැණිය වෙත නොයයි. වැදි ගැහැණිය වෙත නොයයි. කුළුපොතු ගැහැණිය වෙත නොයයි. රථකාර ගැහැණිය වෙත නොයයි. පුක්කුස ගැහැණිය වෙත නොයයි. ගැබ්ගත් ගැහැණිය වෙත නොයයි. දරුවාට කිරි දෙන ගැහැණිය වෙත නොයයි. වැඩිවිය නොපත් ගැහැණිය වෙත නොයයි. ද්‍රෝණය, බ්‍රාහ්මණයා මක් නිසා ද ගැබිණිය වෙත නොයන්නේ ? ඉදින් ද්‍රෝණය, බ්‍රාහ්මණයා ගැබිණිය වෙත යයි නම්, ….(පෙ)…. බ්‍රාහ්මණයා හට බැමිණිය දරු පරපුර බිහි කිරීම පිණිස ම වෙයි. හේ දරුවෙකු හෝ දැරියක උපදවා දරුවාගේ ආශ්වාදය කැමති ව ගිහි ගෙදර වාසය කරයි. ගිහි ගෙයින් නික්ම අනගාරික ව පැවිදි නොවෙයි. යම්තාක් බ්‍රාහ්මණයන්ගේ පැරණි සීමාව ඇද්ද, එහි ම සිටියි. එය නොඉක්මවයි. යම්තාක් බ්‍රාහ්මණයන්ගේ පැරණි සීමාව ඇද්ද, එහි ම සිටියි ද, එය නොඉක්මවයි ද එහෙයින් සීමාව තුළ සිටිය බ්‍රාහ්මණයා යැයි කියනු ලැබේ. මෙසේ ද්‍රෝණය, බ්‍රාහ්මණයා සීමාව තුළ සිටියේ වෙයි. ද්‍රෝණය, බ්‍රාහ්මණයෙක් තම සීමාව බිඳගෙන සිටින්නේ කෙසේ ද? ද්‍රෝණය, මෙහිලා බ්‍රාහ්මණ තෙමේ මව් පසිනුත් පිය පසිනුත් යන දෙපසින් ම සුජාත උපතක් ලද, පිරිසිදු මව් කුසක් ඇති, සත්වෙනි මීමුතු පරපුර තෙක් ජාතිවාදයෙන් නින්දා නොලද, බැහැර නොකළේ වෙයි. හේ සතලිස් අට වර්ෂයක් වේදමන්ත්‍ර හදාරමින් කුමර බඹසර හැසිරෙයි. සතලිස් අට වර්ෂයක් වේදමන්ත්‍ර හදාරමින් කුමර බඹසර හැසිරී ආචාර්යවරයාට ධර්මයෙන් ම ගුරුපඬුරු සොයයි. අධර්මයෙන් නොවෙයි. ද්‍රෝණය, එහිලා ධර්මය යනු කුමක් ද? ගොවිතැනෙනුත් නොවෙයි. වෙළඳාමෙනුත් නොවෙයි. ගවයන් රැකීමෙනුත් නොවෙයි. ධනුශ්ශිල්පයෙනුත් නොවෙයි. රාජපුරුෂ බවෙනුත් නොවෙයි. වෙනත් ශිල්පයකිනුත් නොවෙයි. හුදෙක් ම භික්ෂාවෙහි හැසිරීමෙන් අතට ගත් කබලට අවමන් නොකරමින් වෙසෙයි. හේ ආචාර්යවරයාට ගුරුපඬුරු සොයා දී ධර්මයෙනුත්, අධර්මයෙනුත් බිරිඳක් සොයයි. මිලට ගන්නේ ත් වෙයි, විකුණන්නේ ත් වෙයි. අතපැන් වත්කොට දෙන බැමිණියකුත් සොයයි. හේ බැමිණිය ළඟට ත් යයි. ක්ෂත්‍රීය ගැහැණිය ළඟට ත් යයි. වෛශ්‍ය ගැහැණිය ළඟට ත් යයි. ශුද්‍ර ගැහැණිය ළඟට ත් යයි. සැඩොල් ගැහැණිය ළඟට ත් යයි. වැදි ගැහැණිය ළඟට ත් යයි. කුළුපොතු ගැහැණිය ළඟට ත් යයි. රථකාර ගැහැණිය ළඟට ත් යයි. පුක්කුස ගැහැණිය ළඟට ත් යයි. ගැබ්ගත් ගැහැණිය ළඟට ත් යයි. දරුවාට කිරි දෙන ගැහැණිය ළඟට ත් යයි. වැඩිවිය නොපත් ගැහැණිය ළඟට ත් යයි. බ්‍රාහ්මණයා හට බැමිණිය කාමයෙහි අරුත සපයන්නී ද වෙයි. ජවයෙහි අරුත සපයන්නී ද වෙයි. රතියෙහි අරුත සපයන්නී ද වෙයි. දරු පරපුර බිහි කිරීම ම පිණිස නොවෙයි. යම්තාක් බ්‍රාහ්මණයන්ගේ පැරණි සීමාව ඇද්ද, එහි නොසිටියි. එය ඉක්මවයි. යම්තාක් බ්‍රාහ්මණයන්ගේ පැරණි සීමාව ඇද්ද, එහි නොසිටියි ද, එය ඉක්මවයි ද එහෙයින් සීමාව බිඳගත් බ්‍රාහ්මණයා යැයි කියනු ලැබේ. මෙසේ ද්‍රෝණය, බ්‍රාහ්මණයා සීමාව බිඳගෙන සිටියේ වෙයි. ද්‍රෝණය, බ්‍රාහ්මණයෙක් සැඩොලා හා සමාන වන්නේ කෙසේ ද? ද්‍රෝණය, මෙහිලා බ්‍රාහ්මණ තෙමේ මව් පසිනුත් පිය පසිනුත් යන දෙපසින් ම සුජාත උපතක් ලද, පිරිසිදු මව් කුසක් ඇති, සත්වෙනි මීමුතු පරපුර තෙක් ජාතිවාදයෙන් නින්දා නොලද, බැහැර නොකළේ වෙයි. හේ සතලිස් අට වර්ෂයක් වේදමන්ත්‍ර හදාරමින් කුමර බඹසර හැසිරෙයි. සතලිස් අට වර්ෂයක් වේදමන්ත්‍ර හදාරමින් කුමර බඹසර හැසිරී ආචාර්යවරයාට ධර්මයෙනුත්, අධර්මයෙනුත් ගුරුපඬුරු සොයයි. ද්‍රෝණය, එහිලා ධර්මය යනු කුමක් ද? ගොවිතැනෙනුත් නොවෙයි. වෙළඳාමෙනුත් නොවෙයි. ගවයන් රැකීමෙනුත් නොවෙයි. ධනුශ්ශිල්පයෙනුත් නොවෙයි. රාජපුරුෂ බවෙනුත් නොවෙයි. වෙනත් ශිල්පයකිනුත් නොවෙයි. හුදෙක් ම භික්ෂාවෙහි හැසිරීමෙන් අතට ගත් කබලට අවමන් නොකරමින් වෙසෙයි. හේ ආචාර්යවරයාට ගුරුපඬුරු සොයා දී ධර්මයෙනුත්, අධර්මයෙනුත් බිරිඳක් සොයයි. මිලට ගන්නේ ත් වෙයි, විකුණන්නේ ත් වෙයි. අතපැන් වත්කොට දෙන බැමිණියකුත් සොයයි. හේ බැමිණිය ළඟට ත් යයි. ක්ෂත්‍රීය ගැහැණිය ළඟට ත් යයි. වෛශ්‍ය ගැහැණිය ළඟට ත් යයි. ශුද්‍ර ගැහැණිය ළඟට ත් යයි. සැඩොල් ගැහැණිය ළඟට ත් යයි. වැදි ගැහැණිය ළඟට ත් යයි. කුළුපොතු ගැහැණිය ළඟට ත් යයි. රථකාර ගැහැණිය ළඟට ත් යයි. පුක්කුස ගැහැණිය ළඟට ත් යයි. ගැබ්ගත් ගැහැණිය ළඟට ත් යයි. දරුවාට කිරි දෙන ගැහැණිය ළඟට ත් යයි. වැඩිවිය නොපත් ගැහැණිය ළඟට ත් යයි. බ්‍රාහ්මණයා හට බැමිණිය කාමයෙහි අරුත සපයන්නී ද වෙයි. ජවයෙහි අරුත සපයන්නී ද වෙයි. රතියෙහි අරුත සපයන්නී ද වෙයි. දරු පරපුර බිහි කිරීම ම පිණිස නොවෙයි. හේ හැම රැකියාවකින් ම ජීවිකාව ගෙනියයි. එවිට බ්‍රාහ්මණයෝ ඔහුගෙන් මෙසේ අසන්නාහු ය. ‘භවත, කුමක් හෙයින් බ්‍රාහ්මණයෙක් යැයි ප්‍රතිඥා දෙමින් හැම රැකියාවකින් ම ජීවත් වන්නෙහි ද?’ එවිට හේ මෙසේ කියයි. ‘භවත, ගින්න යම් සේ පිරිසිදු දේ ත් දවයි ද, අපිරිසිදු දේ ත් දවයි ද, එය හා ගින්න මිශ්‍ර වන්නේ නැත. එසෙයින් ම භවත, සියළු රැකියාවන් කරමින් බ්‍රාහ්මණයා ජීවත් වෙන්නේ නමුත් එය හා ඔහු නොතැවරෙයි.’ සියළු රැකියාවන්ගෙන් ජීවත් වන්නේ ය යන කරුණෙන් ද්‍රෝණය, හේ චණ්ඩාල බ්‍රාහ්මණයා යැයි කියනු ලැබේ. මෙසේ ද්‍රෝණය, බ්‍රාහ්මණයා බ්‍රාහ්මණ චණ්ඩාලයෙක් වෙයි. ද්‍රෝණය, බ්‍රාහ්මණයන්ගේ මන්ත්‍ර රචනා කළ, මන්ත්‍ර පැවසූ, පෙර සිටි ඍෂිවරු වෙත් ද, ඒ ඍෂිවරුන් විසින් ගයන ලද, කියන ලද, රැස් කරන ලද, ඒ පැරණි මන්ත්‍ර පද මෙකල බ්‍රාහ්මණවරු ඒ අනුව ගයත් නම්, ඒ අනුව කියත් නම්, ඒ අනුව හදාරවත් නම්, ඒ අනුව සජ්ඣායනා කරවත් නම්, ඒ අනුව වනපොත් කරවත් නම්, ඒ කවර ඍෂිවරුගේ ද? අට්ටක, වාමක, වාමදේව, වෙස්සාමිත්ත, යමතග්ගී, අංගීරස, භාරද්වාජ, වාසෙට්ඨ, කස්සප, භගු යන මේ දස ඍෂීහු ය. ඔවුහු පස් වැදෑරුම් බමුණන් පණවති. බ්‍රහ්මසම බමුණා ය, දේවසම බමුණා ය, සීමාව තුළ සිටින බමුණා ය, සීමා බිඳගත් බමුණා ය, පස්වෙනි සැඩොල් බමුණා ය වශයෙනි. ද්‍රෝණය, මොවුන් අතුරින් ඔබ අයත් වන්නේ කාට ද?” “භවත් ගෞතමයන් වහන්ස, මෙසේ ඇති කල්හී අපි සැඩොලා හා සමාන බමුණා තරම් වත් නොවටින්නෙමු. භවත් ගෞතමයන් වහන්ස, ඉතා මනහර ය. ….(පෙ)…. අද පටන් මා දිවි හිමියෙන් තෙරුවන් සරණ ගිය උපාසකයෙකු වශයෙන් භවත් ගෞතමයන් වහන්සේ පිළිගන්නා සේක්වා !”",
  "ai_short_intro": "ජාති, කුලය, ශිල්පය යන සංකල්පයන්හි සීමාවන් ඉක්මවා ගිය සත්‍ය වූ මානව ස්වභාවය",
  "ai_detailed_summary": "සැවැත් නුවරදී ද්‍රෝණ බ්‍රාහ්මණයා සහ බුදුරජාණන් වහන්සේ අතර ඇති වූ මෙම සංවාදය මගින් බ්‍රාහ්මණ පරම්පරාවේ විවිධ වර්ගීකරණයන් සහ සැබෑ බ්‍රාහ්මණත්වයේ ලක්ෂණ පිළිබඳව ගැඹුරු විග්‍රහයක් ඉදිරිපත් කෙරේ. මෙහිදී බ්‍රාහ්මණයන් පස් ආකාරයකට බෙදා දැක්විය හැකිය.\n\nපළමුවැන්න බ්‍රහ්මයා හා සමාන බ්‍රාහ්මණයායි. මොහු පිරිසිදු කුලයෙන් උපත ලබා, වසර හතළිස් අටක් වේද මන්ත්‍ර හදාරමින්, කිසිදු අයුක්ති සහගත ජීවිකාවක් නොගනිමින්, හුදෙක් භික්ෂාවෙන් ජීවත් වෙමින්, සතර බ්‍රහ්ම විහාරයන්හි හැසිරී මරණින් මට බඹලොව උපදින උත්තරීතර පුද්ගලයායි. දෙවැන්න දෙවියන් හා සමාන බ්‍රාහ්මණයායි. මොහු ද පිරිසිදු කුලයෙන් උපත ලබා, ධර්මීයව ජීවත් වෙමින්, පරම්පරාව පවත්වාගෙන යාම සඳහා පමණක් සීමා වූ, කාම ආශ්‍රිතව පවා සීමා සහිතව හැසිරෙන පුද්ගලයායි. මෙහිදී ඔහු ගැබිණියන් හෝ කිරි දෙන මව්වරුන් වැනි අසුචි සහිත තැන්වලට නොයමින් තම පිරිසිදුකම රැකගනී.\n\nතෙවැන්න සීමාව තුළ සිටින බ්‍රාහ්මණයායි. මොහු ද පිරිසිදු කුලයෙන් උපත ලබා, ධර්මීයව ජීවත් වෙමින්, තම පවුල් සීමාව තුළ පමණක් රැඳී සිටිමින්, පරම්පරාව ඉදිරියට ගෙන යාම සඳහා පමණක් විවාහ වී ජීවත් වෙයි. හතරවැන්න සීමාව බිඳගත් බ්‍රාහ්මණයායි. මොහු ද පිරිසිදු කුලයෙන් උපත ලැබුවද, විවිධ කුලවල ගැහැණියන් සමඟ සම්බන්ධ වෙමින්, විවිධ ආකාරයේ ජීවිකාවන් හෙබිමින්, තම පාරම්පරික සීමාවන් ඉක්මවා යයි. පස්වැන්න සැඩොල් බ්‍රාහ්මණයා හෙවත් චණ්ඩාල බ්‍රාහ්මණයායි. මොහු සියලු ආකාරයේ රැකියාවන් කරමින් ජීවත් වුවද, ගින්නක් මෙන් කිසිදු අපිරිසිදු දෙයක් තමාට නොතැවරෙන බව පවසමින් බ්‍රාහ්මණත්වය පෙන්වීමට උත්සාහ කරයි.\n\nමෙම සංවාදයේදී අටක, වාමක, වාමදේව, වෙස්සාමිත්ත, යමතග්ගී, අංගීරස, භාරද්වාජ, වාසෙට්ඨ, කස්සප සහ භගු යන දස ඍෂිවරුන්ගේ මන්ත්‍ර පද හදාරන බ්‍රාහ්මණයන් පිළිබඳව ද සඳහන් වේ. අවසානයේ ද්‍රෝණ බ්‍රාහ්මණයා තමා අයත් වන්නේ පහළම මට්ටමේ එන සැඩොල් බ්‍රාහ්මණයාට සමාන පුද්ගලයෙකු ලෙස බවත්, තමා එවැනි උසස් බ්‍රාහ්මණයන් අතර නොමැති බවත් ඉතා නිහතමානීව පිළිගනු ලබයි."
}